Workbook

Sheet Sidewalk Projects - All
B3: Capital Facilities Plan- Sidewalks | AK3: Sidewalks - Scoring Criteria
B4: Project Number | C4: TBD Project List | D4: Roadway | E4: Start | F4: End | G4: Description | H4: Grant Award | I4: Grant Source | J4: Budget | K4: Sidewalk Length | L4: Cost/LF | M4: Multi-Use Path | N4: Cost/LF2 | O4: Ramps | P4: Cost/Ea | Q4: RRFB | R4: Cost/Each | S4: Const. Estimate | T4: Engineering | U4: ROW | V4: Contingency | W4: Total Cost | X4: 2015 Cost Estimates | Y4: Percent Change | Z4: Zoning | AA4: Zoning Score | AB4: Functional Classification | AC4: Vehicle on Ped Accident Data | AD4: Facility within 1/4 Mile | AE4: Cost | AF4: Opportunity | AG4: Grant Eligibility | AH4: Dedicated Funding | AI4: Average Score | AK4: Priority | AL4: Zoning | AM4: Roadway Type | AN4: Pedestrian/Bicycle Accidents | AO4: Facility within 1/4 Mile | AP4: Cost | AQ4: Opportunity | AR4: Grant Eligibility | AS4: Dedicated Funding
A5: 1 | B5: CP-101 | C5: TBD -01 | D5: 16th Street NE | E5: Main Street | F5: Machias Cutoff | G5: Construction of an MUP to connect downtown Lake Stevens to the Centennial Trail. | H5: 2500000 | I5: Federal Capital Transportation | S5: 3600000 | T5: 600000 | U5: 270000 | W5: =SUM(S5:V5) -> 4470000 | X5: 287000 | Y5: =W5/X5 -> 15.574913 | Z5: Multi-Family | AA5: 2 | AB5: 2 | AC5: 2 | AD5: 3 | AE5: =IF(W5<150000,"3",IF(W5<500000,"2",IF(W5>500000,"1"))) -> 1 | AF5: 3 | AG5: 3 | AH5: 2 | AI5: {=SUM(AA5:AH5/8)} -> 2.25 | AK5: High = 3 | AL5: Commercial, incl. School | AM5: Minor Arterial | AN5: More than one Ped/Bicycle Accident | AO5: Adjacent to a medical office | AP5: <$150,000 | AQ5: Public & Political Support is Strong | AR5: Eligible for more than two grants | AS5: Full Funding
A6: 2 | B6: CP-102 | C6: TBD-12 | D6: 123rd Ave NE | E6: 22nd Street NE | F6: North Lakeshore Drive | K6: 650 | L6: 400 | N6: 600 | O6: 10 | P6: 4000 | R6: 2500 | S6: =K6*L6+O6*P6+Q6*R6+M6*N6 -> 300000 | T6: =S6*0.1 -> 30000 | U6: =S6*0.07 -> 21000 | V6: =SUM(S6:U6)*0.2 -> 70200 | W6: =SUM(S6:V6) -> 421200 | X6: 120000 | Y6: =W6/X6 -> 3.51 | Z6: Commercial | AA6: 3 | AB6: 1 | AC6: 1 | AD6: 3 | AE6: =IF(W6<150000,"3",IF(W6<500000,"2",IF(W6>500000,"1"))) -> 2 | AF6: 2 | AG6: 2 | AH6: 1 | AI6: {=SUM(AA6:AH6/8)} -> 1.875 | AM6: Collisions involving pedestrians | AO6: Adjacent to services for the disabled
A7: 3 | B7: CP-103 | C7: TBD-11 | D7: Hartford Drive | E7: 20th St NE | F7: 21st Street NE | K7: 500 | L7: 400 | N7: 600 | O7: 4 | P7: 4000 | R7: 2500 | S7: =K7*L7+O7*P7+Q7*R7+M7*N7 -> 216000 | T7: =S7*0.1 -> 21600 | U7: =S7*0.07 -> 15120 | V7: =SUM(S7:U7)*0.2 -> 50544 | W7: =SUM(S7:V7) -> 303264 | X7: 81000 | Y7: =W7/X7 -> 3.744 | Z7: Commercial | AA7: 3 | AB7: 2 | AC7: 1 | AD7: 3 | AE7: =IF(W7<150000,"3",IF(W7<500000,"2",IF(W7>500000,"1"))) -> 2 | AF7: 3 | AG7: 1 | AH7: 1 | AI7: {=SUM(AA7:AH7/8)} -> 2 | AM7: Streets with highway interchange | AO7: Adjacent to a library
A8: 4 | B8: CP-104 | C8: TBD-10 | D8: Grade Road | E8: Hartford Drive | F8: Library | K8: 650 | L8: 400 | N8: 600 | O8: 2 | P8: 4000 | Q8: 2 | R8: 2500 | S8: =K8*L8+O8*P8+Q8*R8+M8*N8 -> 273000 | T8: =S8*0.1 -> 27300 | U8: =S8*0.07 -> 19110 | V8: =SUM(S8:U8)*0.2 -> 63882 | W8: =SUM(S8:V8) -> 383292 | X8: 135000 | Y8: =W8/X8 -> 2.8392 | Z8: Commercial | AA8: 3 | AB8: 2 | AC8: 1 | AD8: 3 | AE8: =IF(W8<150000,"3",IF(W8<500000,"2",IF(W8>500000,"1"))) -> 2 | AF8: 3 | AG8: 1 | AH8: 1 | AI8: {=SUM(AA8:AH8/8)} -> 2 | AO8: Adjacent to a senior center or senior housing
A9: 5 | B9: CP-105 | D9: Grade Road | E9: 30th Street NE | F9: 32nd Street NE | K9: 500 | L9: 400 | N9: 600 | O9: 4 | P9: 4000 | R9: 2500 | S9: =K9*L9+O9*P9+Q9*R9+M9*N9 -> 216000 | T9: =S9*0.1 -> 21600 | U9: =S9*0.07 -> 15120 | V9: =SUM(S9:U9)*0.2 -> 50544 | W9: =SUM(S9:V9) -> 303264 | X9: 173000 | Y9: =W9/X9 -> 1.7529711 | Z9: Single Family | AA9: 1 | AB9: 2 | AC9: 2 | AD9: 2 | AE9: =IF(W9<150000,"3",IF(W9<500000,"2",IF(W9>500000,"1"))) -> 2 | AF9: 3 | AG9: 1 | AH9: 1 | AI9: {=SUM(AA9:AH9/8)} -> 1.75 | AO9: Adjacent to a school
A10: 6 | B10: CP-106 | D10: Cedar Road | E10: 20th Street NE | F10: Forest Road | K10: 1400 | L10: 400 | N10: 600 | O10: 2 | P10: 4000 | R10: 2500 | S10: =K10*L10+O10*P10+Q10*R10+M10*N10 -> 568000 | T10: =S10*0.1 -> 56800 | U10: =S10*0.07 -> 39760 | V10: =SUM(S10:U10)*0.2 -> 132912 | W10: =SUM(S10:V10) -> 797472 | X10: 209000 | Y10: =W10/X10 -> 3.8156555 | Z10: Single Family | AA10: 1 | AB10: 1 | AC10: 1 | AD10: 1 | AE10: =IF(W10<150000,"3",IF(W10<500000,"2",IF(W10>500000,"1"))) -> 1 | AF10: 1 | AG10: 1 | AH10: 1 | AI10: {=SUM(AA10:AH10/8)} -> 1 | AO10: Adjacent to a high use transit stop
A11: 7 | B11: CP-107 | C11: TBD-04 | D11: 117th Ave NE | E11: 20th Street NE | F11: 26th Street NE | G11: TBD sidewalk along one side of 117th Ave NE between 20th St and26th St. Includes ROW and typical frontage improvements including stormwater. | S11: 1170000 | T11: 290000 | W11: =SUM(S11:V11) -> 1460000 | X11: 434000 | Y11: =W11/X11 -> 3.3640553 | Z11: Single Family | AA11: 1 | AB11: 2 | AC11: 3 | AD11: 3 | AE11: =IF(W11<150000,"3",IF(W11<500000,"2",IF(W11>500000,"1"))) -> 1 | AF11: 2 | AG11: 2 | AH11: 3 | AI11: {=SUM(AA11:AH11/8)} -> 2.125
A12: 8 | B12: CP-108 | D12: Lake View Drive | E12: 112th DR NE | F12: Callow Road | K12: 3000 | L12: 400 | N12: 600 | O12: 8 | P12: 4000 | R12: 2500 | S12: =K12*L12+O12*P12+Q12*R12+M12*N12 -> 1232000 | T12: =S12*0.1 -> 123200 | U12: =S12*0.07 -> 86240 | V12: =SUM(S12:U12)*0.2 -> 288288 | W12: =SUM(S12:V12) -> 1729728 | X12: 1070000 | Y12: =W12/X12 -> 1.6165682 | Z12: Single Family | AA12: 1 | AB12: 2 | AC12: 1 | AD12: 1 | AE12: =IF(W12<150000,"3",IF(W12<500000,"2",IF(W12>500000,"1"))) -> 1 | AF12: 3 | AG12: 2 | AH12: 1 | AI12: {=SUM(AA12:AH12/8)} -> 1.5 | AK12: Medium = 2 | AL12: Mixed Use | AM12: Major Collector | AN12: One Ped/Bicycle Accident | AO12: Adjacent to a public office | AP12: $150,001 to $500,000 | AQ12: Public or Political Support Strong | AR12: Eligible for one grant | AS12: >50% Funded
A13: 9 | B13: CP-110 | D13: Cedar Road | E13: Forest Road | F13: 28th Street NE | K13: 1400 | L13: 400 | N13: 600 | P13: 4000 | R13: 2500 | S13: =K13*L13+O13*P13+Q13*R13+M13*N13 -> 560000 | T13: =S13*0.1 -> 56000 | U13: =S13*0.07 -> 39200 | V13: =SUM(S13:U13)*0.2 -> 131040 | W13: =SUM(S13:V13) -> 786240 | X13: 523000 | Y13: =W13/X13 -> 1.503327 | Z13: Single Family | AA13: 1 | AB13: 1 | AC13: 1 | AD13: 3 | AE13: =IF(W13<150000,"3",IF(W13<500000,"2",IF(W13>500000,"1"))) -> 1 | AF13: 1 | AG13: 1 | AH13: 1 | AI13: {=SUM(AA13:AH13/8)} -> 1.25 | AM13: Minor Collector
A14: 10 | B14: CP-111 | D14: Lake Drive | E14: Lundeen Parkway | F14: 28th Street NE | K14: 1500 | L14: 400 | N14: 600 | O14: 2 | P14: 4000 | R14: 2500 | S14: =K14*L14+O14*P14+Q14*R14+M14*N14 -> 608000 | T14: =S14*0.1 -> 60800 | U14: =S14*0.07 -> 42560 | V14: =SUM(S14:U14)*0.2 -> 142272 | W14: =SUM(S14:V14) -> 853632 | X14: 597000 | Y14: =W14/X14 -> 1.4298693 | Z14: Single Family | AA14: 1 | AB14: 2 | AC14: 1 | AD14: 1 | AE14: =IF(W14<150000,"3",IF(W14<500000,"2",IF(W14>500000,"1"))) -> 1 | AF14: 1 | AG14: 1 | AH14: 1 | AI14: {=SUM(AA14:AH14/8)} -> 1.125 | AO14: Adjacent to a park
A15: 11 | B15: CP-112 | C15: TBD-07 | D15: Soper Hill | E15: Lake Drive | F15: RAB at SR9 | G15: TBD sidewalk along one side of Soper Hill Rd between Lake Dr and SR9. Includes ROW and typical frontage improvements including stormwater. | S15: 1100000 | T15: 275000 | W15: =SUM(S15:V15) -> 1375000 | X15: 1031000 | Y15: =W15/X15 -> 1.3336566 | Z15: Commercial | AA15: 3 | AB15: 3 | AC15: 1 | AD15: 3 | AE15: =IF(W15<150000,"3",IF(W15<500000,"2",IF(W15>500000,"1"))) -> 1 | AF15: 3 | AG15: 2 | AH15: 1 | AI15: {=SUM(AA15:AH15/8)} -> 2.125
A16: 12 | B16: CP-116 | C16: TBD-20 | D16: 4th Street NE | E16: 97th Drive NE | F16: 98th Drive NE | K16: 450 | L16: 400 | N16: 600 | O16: 2 | P16: 4000 | R16: 2500 | S16: =K16*L16+O16*P16+Q16*R16+M16*N16 -> 188000 | T16: =S16*0.1 -> 18800 | U16: =S16*0.07 -> 13160 | V16: =SUM(S16:U16)*0.2 -> 43992 | W16: =SUM(S16:V16) -> 263952 | X16: 163000 | Y16: =W16/X16 -> 1.6193374 | Z16: Multi-Family | AA16: 2 | AB16: 1 | AC16: 1 | AD16: 3 | AE16: =IF(W16<150000,"3",IF(W16<500000,"2",IF(W16>500000,"1"))) -> 2 | AF16: 2 | AG16: 1 | AH16: 1 | AI16: {=SUM(AA16:AH16/8)} -> 1.625
A17: 13 | B17: CP-117 | D17: 99th Ave NE | E17: Lakemont Avenue | F17: 3rd Street NE | K17: 550 | L17: 400 | N17: 600 | O17: 2 | P17: 4000 | R17: 2500 | S17: =K17*L17+O17*P17+Q17*R17+M17*N17 -> 228000 | T17: =S17*0.1 -> 22800 | U17: =S17*0.07 -> 15960 | V17: =SUM(S17:U17)*0.2 -> 53352 | W17: =SUM(S17:V17) -> 320112 | X17: 230000 | Y17: =W17/X17 -> 1.3917913 | Z17: Single Family | AA17: 1 | AB17: 1 | AC17: 1 | AD17: 3 | AE17: =IF(W17<150000,"3",IF(W17<500000,"2",IF(W17>500000,"1"))) -> 2 | AF17: 2 | AG17: 1 | AH17: 1 | AI17: {=SUM(AA17:AH17/8)} -> 1.5 | AK17: Low = 1 | AL17: Single Family | AM17: Neighborhood | AN17: No Record | AO17: Connects or completes street(s) | AP17: >$500,000 | AQ17: Support Not Known/Not Supportive | AR17: Eligibility Unknown | AS17: <50% Funded
A18: 14 | B18: CP-118 | C18: TBD-14 | D18: 99th Ave NE | E18: 1st Street NE | F18: Chapel Hill Road | K18: 160 | L18: 400 | N18: 600 | O18: 2 | P18: 4000 | R18: 2500 | S18: =K18*L18+O18*P18+Q18*R18+M18*N18 -> 72000 | T18: =S18*0.1 -> 7200 | U18: =S18*0.07 -> 5040 | V18: =SUM(S18:U18)*0.2 -> 16848 | W18: =SUM(S18:V18) -> 101088 | X18: 198000 | Y18: =W18/X18 -> 0.51054545 | Z18: Multi-Family | AA18: 2 | AB18: 2 | AC18: 1 | AD18: 3 | AE18: =IF(W18<150000,"3",IF(W18<500000,"2",IF(W18>500000,"1"))) -> 3 | AF18: 2 | AG18: 1 | AH18: 1 | AI18: {=SUM(AA18:AH18/8)} -> 1.875 | AL18: Industrial
A19: 15 | B19: CP-119 | D19: 99th Ave NE | E19: Market Place | F19: 4th Street SE | K19: 1350 | L19: 400 | N19: 600 | O19: 4 | P19: 4000 | R19: 2500 | S19: =K19*L19+O19*P19+Q19*R19+M19*N19 -> 556000 | T19: =S19*0.1 -> 55600 | U19: =S19*0.07 -> 38920 | V19: =SUM(S19:U19)*0.2 -> 130104 | W19: =SUM(S19:V19) -> 780624 | X19: 507000 | Y19: =W19/X19 -> 1.5396923 | Z19: Single Family | AA19: 1 | AB19: 2 | AC19: 1 | AD19: 3 | AE19: =IF(W19<150000,"3",IF(W19<500000,"2",IF(W19>500000,"1"))) -> 1 | AF19: 2 | AG19: 1 | AH19: 1 | AI19: {=SUM(AA19:AH19/8)} -> 1.5
A20: 16 | B20: CP-120 | D20: 99th Ave SE | E20: 11th Place SE | F20: 4th Street SE | K20: 2500 | L20: 400 | N20: 600 | O20: 6 | P20: 4000 | R20: 2500 | S20: =K20*L20+O20*P20+Q20*R20+M20*N20 -> 1024000 | T20: =S20*0.1 -> 102400 | U20: =S20*0.07 -> 71680 | V20: =SUM(S20:U20)*0.2 -> 239616 | W20: =SUM(S20:V20) -> 1437696 | X20: 159000 | Y20: =W20/X20 -> 9.0421132 | Z20: Single Family | AA20: 1 | AB20: 2 | AC20: 1 | AD20: 1 | AE20: =IF(W20<150000,"3",IF(W20<500000,"2",IF(W20>500000,"1"))) -> 1 | AF20: 2 | AG20: 1 | AH20: 1 | AI20: {=SUM(AA20:AH20/8)} -> 1.25
A21: 17 | B21: CP-121 | D21: 32nd Street NE | E21: Grade Road | F21: 118th Drive NE | K21: 450 | L21: 400 | N21: 600 | O21: 2 | P21: 4000 | R21: 2500 | S21: =K21*L21+O21*P21+Q21*R21+M21*N21 -> 188000 | T21: =S21*0.1 -> 18800 | U21: =S21*0.07 -> 13160 | V21: =SUM(S21:U21)*0.2 -> 43992 | W21: =SUM(S21:V21) -> 263952 | X21: 814000 | Y21: =W21/X21 -> 0.32426536 | Z21: Single Family | AA21: 1 | AB21: 1 | AC21: 1 | AD21: 1 | AE21: =IF(W21<150000,"3",IF(W21<500000,"2",IF(W21>500000,"1"))) -> 2 | AF21: 1 | AG21: 1 | AH21: 1 | AI21: {=SUM(AA21:AH21/8)} -> 1.125
A22: 18 | B22: CP-122 | D22: 8th Street SE | E22: 79th Ave SE | F22: 83rd Ave SE | K22: 1300 | L22: 400 | N22: 600 | O22: 3 | P22: 4000 | R22: 2500 | S22: =K22*L22+O22*P22+Q22*R22+M22*N22 -> 532000 | T22: =S22*0.1 -> 53200 | U22: =S22*0.07 -> 37240 | V22: =SUM(S22:U22)*0.2 -> 124488 | W22: =SUM(S22:V22) -> 746928 | X22: 476000 | Y22: =W22/X22 -> 1.5691765 | Z22: Single Family | AA22: 1 | AB22: 2 | AC22: 1 | AD22: 1 | AE22: =IF(W22<150000,"3",IF(W22<500000,"2",IF(W22>500000,"1"))) -> 1 | AF22: 2 | AG22: 1 | AH22: 1 | AI22: {=SUM(AA22:AH22/8)} -> 1.25 | AK22: Adjacent is within 1/4 mile
A23: 19 | B23: CP-123 | D23: 79th Ave SE | E23: 8th Street SE | F23: 12th Street SE | K23: 1300 | L23: 400 | N23: 600 | O23: 2 | P23: 4000 | R23: 2500 | S23: =K23*L23+O23*P23+Q23*R23+M23*N23 -> 528000 | T23: =S23*0.1 -> 52800 | U23: =S23*0.07 -> 36960 | V23: =SUM(S23:U23)*0.2 -> 123552 | W23: =SUM(S23:V23) -> 741312 | X23: 477000 | Y23: =W23/X23 -> 1.5541132 | Z23: Single Family | AA23: 1 | AB23: 2 | AC23: 1 | AD23: 2 | AE23: =IF(W23<150000,"3",IF(W23<500000,"2",IF(W23>500000,"1"))) -> 1 | AF23: 2 | AG23: 1 | AH23: 1 | AI23: {=SUM(AA23:AH23/8)} -> 1.375
A24: 20 | B24: CP-124 | C24: TBD-18 | D24: S. Lake Stevens Road MUP Phase III | E24: East Lakeshore Drive S Lake Stevens Rd | F24: 123rd Street SE | G24: Construction of MUP to connect pedestrian generators to the existing trail. | I24: Federal Capital Transportation | S24: 3000000 | T24: =S24*0.1 -> 300000 | U24: 200000 | W24: =SUM(S24:V24) -> 3500000 | X24: 1157000 | Y24: =W24/X24 -> 3.0250648 | Z24: Single Family | AA24: 1 | AB24: 3 | AC24: 2 | AD24: 1 | AE24: =IF(W24<150000,"3",IF(W24<500000,"2",IF(W24>500000,"1"))) -> 1 | AF24: 3 | AG24: 2 | AH24: 1 | AI24: {=SUM(AA24:AH24/8)} -> 1.75
A25: 21 | B25: CP-125 | D25: Vernon Road | E25: 12th Place NE | F25: 15th Street NE | K25: 600 | L25: 400 | N25: 600 | O25: 4 | P25: 4000 | R25: 2500 | S25: =K25*L25+O25*P25+Q25*R25+M25*N25 -> 256000 | T25: =S25*0.1 -> 25600 | U25: =S25*0.07 -> 17920 | V25: =SUM(S25:U25)*0.2 -> 59904 | W25: =SUM(S25:V25) -> 359424 | X25: 266000 | Y25: =W25/X25 -> 1.351218 | Z25: Single Family | AA25: 1 | AB25: 1 | AC25: 1 | AD25: 2 | AE25: =IF(W25<150000,"3",IF(W25<500000,"2",IF(W25>500000,"1"))) -> 2 | AF25: 2 | AG25: 1 | AH25: 1 | AI25: {=SUM(AA25:AH25/8)} -> 1.375 | AL25: Sources
B26: CP-126S | C26: TBD-19 | D26: 20th Street SE | E26: S. Lake Stevens Road | F26: 113th Drive SE | K26: 2000 | L26: 400 | N26: 600 | P26: 4000 | Q26: 8 | R26: 2500 | S26: =K26*L26+O26*P26+Q26*R26+M26*N26 -> 820000 | T26: =S26*0.1 -> 82000 | U26: =S26*0.07 -> 57400 | V26: =SUM(S26:U26)*0.2 -> 191880 | W26: =SUM(S26:V26) -> 1151280 | Z26: Single Family | AA26: 1 | AB26: 3 | AC26: 2 | AD26: 2 | AE26: =IF(W26<150000,"3",IF(W26<500000,"2",IF(W26>500000,"1"))) -> 1 | AF26: 2 | AG26: 1 | AH26: 1 | AI26: {=SUM(AA26:AH26/8)} -> 1.625 | AL26: 2015 Sidewalk Master Plan
B27: CP-127S | C27: TBD-02 | D27: 91st Ave SE | E27: 4th St. SE | F27: Market Street | G27: TBD sidewalk along the east side of 91st Ave SE between 4th and Market. Includes ROW and typical frontage improvements including stormwater. | S27: 760000 | T27: 175000 | W27: =SUM(S27:V27) -> 935000 | Z27: Single Family | AA27: 3 | AB27: 2 | AC27: 2 | AD27: 3 | AE27: =IF(W27<150000,"3",IF(W27<500000,"2",IF(W27>500000,"1"))) -> 1 | AF27: 3 | AG27: 3 | AH27: 1 | AI27: {=SUM(AA27:AH27/8)} -> 2.25 | AL27: Subarea Plans
B28: CP-128S | C28: TBD-03 | D28: 91st Ave SE | E28: 8th Street SE | F28: 4th Street SE | G28: TBD sidewalk along the east side of 91st Ave SE between 8th and 4th. Includes ROW and typical frontage improvements including stormwater. | S28: 405000 | T28: 100000 | W28: =SUM(S28:V28) -> 505000 | Z28: Single Family | AA28: 3 | AB28: 2 | AC28: 2 | AD28: 3 | AE28: =IF(W28<150000,"3",IF(W28<500000,"2",IF(W28>500000,"1"))) -> 1 | AF28: 3 | AG28: 3 | AH28: 1 | AI28: {=SUM(AA28:AH28/8)} -> 2.25 | AL28: 2022 - Local Road Safety Plan (Accident Data)
B29: CP-129S | C29: TBD-13 | D29: 83rd Ave NE | E29: 20th Street SE | F29: 17th Street SE | K29: 850 | L29: 400 | N29: 600 | P29: 4000 | R29: 2500 | S29: =K29*L29+O29*P29+Q29*R29+M29*N29 -> 340000 | T29: =S29*0.1 -> 34000 | U29: =S29*0.07 -> 23800 | V29: =SUM(S29:U29)*0.2 -> 79560 | W29: =SUM(S29:V29) -> 477360 | Z29: Commercial | AA29: 3 | AB29: 2 | AC29: 1 | AD29: 3 | AE29: =IF(W29<150000,"3",IF(W29<500000,"2",IF(W29>500000,"1"))) -> 2 | AF29: 2 | AG29: 1 | AH29: 1 | AI29: {=SUM(AA29:AH29/8)} -> 1.875 | AL29: WSDOT Functional Classification Web Portal
B30: CP-130S | D30: 103rd Ave SE | E30: 32nd Street NE | F30: South Lake Stevens Road | K30: 0 | L30: 400 | N30: 600 | O30: 12 | P30: 4000 | Q30: 4 | R30: 2500 | S30: =K30*L30+O30*P30+Q30*R30+M30*N30 -> 58000 | T30: =S30*0.1 -> 5800 | U30: =S30*0.07 -> 4060 | V30: =SUM(S30:U30)*0.2 -> 13572 | W30: =SUM(S30:V30) -> 81432 | Z30: Single Family | AA30: 1 | AB30: 2 | AC30: 1 | AD30: 3 | AE30: =IF(W30<150000,"3",IF(W30>150000,"2",IF(W30>500000,"1"))) -> 3 | AF30: 2 | AG30: 2 | AH30: 1 | AI30: {=SUM(AA30:AH30/8)} -> 1.875 | AL30: StreetLogix
B31: CP-132S | C31: TBD-08 | D31: 113th Ave NE | E31: 32nd Street NE | F31: 36th Street NE | K31: 0 | L31: 400 | N31: 600 | O31: 11 | P31: 4000 | Q31: 2 | R31: 2500 | S31: =K31*L31+O31*P31+Q31*R31+M31*N31 -> 49000 | T31: =S31*0.1 -> 4900 | U31: =S31*0.07 -> 3430 | V31: =SUM(S31:U31)*0.2 -> 11466 | W31: =SUM(S31:V31) -> 68796 | Z31: Commercial | AA31: 3 | AB31: 1 | AC31: 1 | AD31: 3 | AE31: =IF(W31<150000,"3",IF(W31>150000,"2",IF(W31>500000,"1"))) -> 3 | AF31: 2 | AG31: 2 | AH31: 1 | AI31: {=SUM(AA31:AH31/8)} -> 2
B32: CP-133S | D32: 131st Ave NE | E32: 20th Street NE | F32: Hartford Road | K32: 1800 | L32: 400 | N32: 600 | O32: 2 | P32: 4000 | Q32: 2 | R32: 2500 | S32: =K32*L32+O32*P32+Q32*R32+M32*N32 -> 733000 | T32: =S32*0.1 -> 73300 | U32: =S32*0.07 -> 51310 | V32: =SUM(S32:U32)*0.2 -> 171522 | W32: =SUM(S32:V32) -> 1029132 | Z32: Industrial | AA32: 1 | AB32: 1 | AC32: 1 | AD32: 3 | AE32: =IF(W32<150000,"3",IF(W32<500000,"2",IF(W32>500000,"1"))) -> 1 | AF32: 1 | AG32: 1 | AH32: 1 | AI32: {=SUM(AA32:AH32/8)} -> 1.25
B33: CP-135S | C33: TBD-16 | D33: 99th Ave NE | E33: Sunnycrest Elem. | F33: 30th Street NE | K33: 1300 | L33: 400 | N33: 600 | O33: 2 | P33: 4000 | R33: 2500 | S33: =K33*L33+O33*P33+Q33*R33+M33*N33 -> 528000 | T33: =S33*0.1 -> 52800 | U33: =S33*0.07 -> 36960 | V33: =SUM(S33:U33)*0.2 -> 123552 | W33: =SUM(S33:V33) -> 741312 | Z33: Single Family | AA33: 1 | AB33: 2 | AC33: 1 | AD33: 3 | AE33: =IF(W33<150000,"3",IF(W33<500000,"2",IF(W33>500000,"1"))) -> 1 | AF33: 3 | AG33: 2 | AH33: 1 | AI33: {=SUM(AA33:AH33/8)} -> 1.75
B34: CP-136S | D34: 8th Street SE | E34: 79th Ave SE | F34: 91st Avenue SE | K34: 2500 | L34: 400 | N34: 600 | O34: 4 | P34: 4000 | Q34: 2 | R34: 2500 | S34: =K34*L34+O34*P34+Q34*R34+M34*N34 -> 1021000 | T34: =S34*0.1 -> 102100 | U34: =S34*0.07 -> 71470 | V34: =SUM(S34:U34)*0.2 -> 238914 | W34: =SUM(S34:V34) -> 1433484 | Z34: Single Family | AA34: 1 | AB34: 2 | AC34: 1 | AD34: 2 | AE34: =IF(W34<150000,"3",IF(W34<500000,"2",IF(W34>500000,"1"))) -> 1 | AF34: 2 | AG34: 1 | AH34: 1 | AI34: {=SUM(AA34:AH34/8)} -> 1.375
B35: CP-137S | D35: 30th Street NE | E35: 99th Ave NE | F35: Callow Road | K35: 1200 | L35: 400 | N35: 600 | O35: 4 | P35: 4000 | Q35: 2 | R35: 2500 | S35: =K35*L35+O35*P35+Q35*R35+M35*N35 -> 501000 | T35: =S35*0.1 -> 50100 | U35: =S35*0.07 -> 35070 | V35: =SUM(S35:U35)*0.2 -> 117234 | W35: =SUM(S35:V35) -> 703404 | Z35: Single Family | AA35: 1 | AB35: 1 | AC35: 2 | AD35: 3 | AE35: =IF(W35<150000,"3",IF(W35<500000,"2",IF(W35>500000,"1"))) -> 1 | AF35: 1 | AG35: 1 | AH35: 1 | AI35: {=SUM(AA35:AH35/8)} -> 1.375
B36: CP-138S | D36: Cedar Road | E36: 20th St. NE | F36: 30th Street NE | K36: 3400 | L36: 400 | N36: 600 | O36: 6 | P36: 4000 | Q36: 2 | R36: 2500 | S36: =K36*L36+O36*P36+Q36*R36+M36*N36 -> 1389000 | T36: =S36*0.1 -> 138900 | U36: =S36*0.07 -> 97230 | V36: =SUM(S36:U36)*0.2 -> 325026 | W36: =SUM(S36:V36) -> 1950156 | Z36: Single Family | AA36: 1 | AB36: 1 | AC36: 1 | AD36: 3 | AE36: =IF(W36<150000,"3",IF(W36<500000,"2",IF(W36>500000,"1"))) -> 1 | AF36: 1 | AG36: 1 | AH36: 1 | AI36: {=SUM(AA36:AH36/8)} -> 1.25
B37: CP-139S | C37: TBD-09 | D37: 20th Street NE | E37: Main Street | F37: 131st Ave SE | K37: 0 | L37: 400 | N37: 600 | O37: 4 | P37: 4000 | Q37: 2 | R37: 2500 | S37: =K37*L37+O37*P37+Q37*R37+M37*N37 -> 21000 | T37: =S37*0.1 -> 2100 | U37: =S37*0.07 -> 1470 | V37: =SUM(S37:U37)*0.2 -> 4914 | W37: =SUM(S37:V37) -> 29484 | Z37: Commercial | AA37: 3 | AB37: 3 | AC37: 1 | AD37: 3 | AE37: =IF(W37<150000,"3",IF(W37>150000,"2",IF(W37>500000,"1"))) -> 3 | AF37: 1 | AG37: 1 | AH37: 1 | AI37: {=SUM(AA37:AH37/8)} -> 2
B38: CP-140S | D38: S. Lake Stevens Road MUP Phase II | E38: 18th St SE | F38: SR 9 | G38: Construction of MUP to connect pedestrian generators to the existing trail. | H38: 3000000 | I38: Federal Capital Transportation | S38: 3000000 | T38: =S38*0.1 -> 300000 | U38: 340000 | W38: =SUM(S38:V38) -> 3640000 | Z38: Multi-Family | AA38: 2 | AB38: 2 | AC38: 1 | AD38: 3 | AE38: =IF(W38<150000,"3",IF(W38<500000,"2",IF(W38>500000,"1"))) -> 1 | AF38: 3 | AG38: 2 | AH38: 3 | AI38: {=SUM(AA38:AH38/8)} -> 2.125
B39: CP-141S | C39: TBD-06 | D39: North Lakeshore Drive | E39: Main Street | F39: 123rd Ave NE | G39: TBD sidewalk along one side of N Lakeshore Dr between Main St and 123rd Ave. | S39: 120000 | T39: 30000 | W39: =SUM(S39:V39) -> 150000 | Z39: Commercial | AA39: 3 | AB39: 2 | AC39: 2 | AD39: 2 | AE39: =IF(W39<150000,"3",IF(W39<500000,"2",IF(W39>500000,"1"))) -> 2 | AF39: 2 | AG39: 2 | AH39: 1 | AI39: {=SUM(AA39:AH39/8)} -> 2
B40: CP-142S | C40: TBD-15 | D40: North Lakeshore Drive | E40: 123rd Ave NE | F40: North Lakeshore Swim Beach | K40: 1200 | L40: 400 | N40: 600 | O40: 2 | P40: 4000 | Q40: 2 | R40: 2500 | S40: =K40*L40+O40*P40+Q40*R40+M40*N40 -> 493000 | T40: =S40*0.1 -> 49300 | U40: =S40*0.07 -> 34510 | V40: =SUM(S40:U40)*0.2 -> 115362 | W40: =SUM(S40:V40) -> 692172 | Z40: Commercial | AA40: 3 | AB40: 2 | AC40: 1 | AD40: 2 | AE40: =IF(W40<150000,"3",IF(W40<500000,"2",IF(W40>500000,"1"))) -> 1 | AF40: 3 | AG40: 2 | AH40: 1 | AI40: {=SUM(AA40:AH40/8)} -> 1.875
B41: CP-143S | D41: North Lakeshore Drive | E41: Mitchell Road | F41: 114th Drive NE | K41: 1600 | L41: 400 | N41: 600 | O41: 4 | P41: 4000 | R41: 2500 | S41: =K41*L41+O41*P41+Q41*R41+M41*N41 -> 656000 | T41: =S41*0.1 -> 65600 | U41: =S41*0.07 -> 45920 | V41: =SUM(S41:U41)*0.2 -> 153504 | W41: =SUM(S41:V41) -> 921024 | Z41: Single Family | AA41: 1 | AB41: 2 | AC41: 1 | AD41: 1 | AE41: =IF(W41<150000,"3",IF(W41<500000,"2",IF(W41>500000,"1"))) -> 1 | AF41: 3 | AG41: 1 | AH41: 1 | AI41: {=SUM(AA41:AH41/8)} -> 1.375
B42: CP-144S | D42: 79th Ave SE | E42: 16th Place SE | F42: 14th Street SE | K42: 360 | L42: 400 | N42: 600 | P42: 4000 | Q42: 2 | R42: 2500 | S42: =K42*L42+O42*P42+Q42*R42+M42*N42 -> 149000 | T42: =S42*0.1 -> 14900 | U42: =S42*0.07 -> 10430 | V42: =SUM(S42:U42)*0.2 -> 34866 | W42: =SUM(S42:V42) -> 209196 | Z42: Single Family | AA42: 1 | AB42: 2 | AC42: 1 | AD42: 2 | AE42: =IF(W42<150000,"3",IF(W42<500000,"2",IF(W42>500000,"1"))) -> 2 | AF42: 2 | AG42: 1 | AH42: 1 | AI42: {=SUM(AA42:AH42/8)} -> 1.5
B43: CP-145S | D43: 79th Ave SE | E43: 14th Street NE | F43: 10th Street SE | K43: 1100 | L43: 400 | N43: 600 | P43: 4000 | Q43: 4 | R43: 2500 | S43: =K43*L43+O43*P43+Q43*R43+M43*N43 -> 450000 | T43: =S43*0.1 -> 45000 | U43: =S43*0.07 -> 31500 | V43: =SUM(S43:U43)*0.2 -> 105300 | W43: =SUM(S43:V43) -> 631800 | Z43: Single Family | AA43: 1 | AB43: 2 | AC43: 1 | AD43: 2 | AE43: =IF(W43<150000,"3",IF(W43<500000,"2",IF(W43>500000,"1"))) -> 1 | AF43: 2 | AG43: 1 | AH43: 1 | AI43: {=SUM(AA43:AH43/8)} -> 1.375
B44: CP-146S | D44: Frontier Circle | E44: Frontier Circle East | F44: 11th Street SE | K44: 1000 | L44: 400 | N44: 600 | O44: 4 | P44: 4000 | R44: 2500 | S44: =K44*L44+O44*P44+Q44*R44+M44*N44 -> 416000 | T44: =S44*0.1 -> 41600 | U44: =S44*0.07 -> 29120 | V44: =SUM(S44:U44)*0.2 -> 97344 | W44: =SUM(S44:V44) -> 584064 | Z44: Single Family | AA44: 1 | AB44: 1 | AC44: 1 | AD44: 2 | AE44: =IF(W44<150000,"3",IF(W44<500000,"2",IF(W44>500000,"1"))) -> 1 | AF44: 3 | AG44: 1 | AH44: 1 | AI44: {=SUM(AA44:AH44/8)} -> 1.375
B45: CP-147S | D45: Hartford Drive | E45: 21st Street NE | F45: 131st Ave NE | K45: 0 | L45: 400 | M45: 2450 | N45: 600 | O45: 2 | P45: 4000 | R45: 2500 | S45: =K45*L45+O45*P45+Q45*R45+M45*N45 -> 1478000 | T45: =S45*0.1 -> 147800 | U45: =S45*0.07 -> 103460 | V45: =SUM(S45:U45)*0.2 -> 345852 | W45: =SUM(S45:V45) -> 2075112 | Z45: Single Family | AA45: 1 | AB45: 1 | AC45: 1 | AD45: 3 | AE45: =IF(W45<150000,"3",IF(W45<500000,"2",IF(W45>500000,"1"))) -> 1 | AF45: 3 | AG45: 1 | AH45: 1 | AI45: {=SUM(AA45:AH45/8)} -> 1.5
B46: CP-148S | D46: 118th Ave SE | E46: Machias | F46: Meridian | K46: 4300 | L46: 400 | N46: 600 | O46: 8 | P46: 4000 | R46: 2500 | S46: =K46*L46+O46*P46+Q46*R46+M46*N46 -> 1752000 | T46: =S46*0.1 -> 175200 | U46: =S46*0.07 -> 122640 | V46: =SUM(S46:U46)*0.2 -> 409968 | W46: =SUM(S46:V46) -> 2459808 | Z46: Single Family | AA46: 1 | AB46: 1 | AC46: 1 | AD46: 1 | AE46: =IF(W46<150000,"3",IF(W46<500000,"2",IF(W46>500000,"1"))) -> 1 | AF46: 2 | AG46: 1 | AH46: 1 | AI46: {=SUM(AA46:AH46/8)} -> 1.125
B47: CP-149S | D47: East Lakeshore | E47: S. Lake Stevens Road | F47: Sunset Beach | K47: 0 | L47: 400 | M47: 5000 | N47: 600 | P47: 4000 | R47: 2500 | S47: =K47*L47+O47*P47+Q47*R47+M47*N47 -> 3000000 | T47: =S47*0.1 -> 300000 | U47: =S47*0.07 -> 210000 | V47: =SUM(S47:U47)*0.2 -> 702000 | W47: =SUM(S47:V47) -> 4212000 | Z47: Single Family | AA47: 1 | AB47: 2 | AC47: 2 | AD47: 1 | AE47: =IF(W47<150000,"3",IF(W47<500000,"2",IF(W47>500000,"1"))) -> 1 | AF47: 2 | AG47: 1 | AH47: 1 | AI47: {=SUM(AA47:AH47/8)} -> 1.375
B48: CP-150S | C48: TBD-17 | D48: 99th Ave SE | E48: 20th St. SE | F48: 8th St. SE | K48: =1800+1200 -> 3000 | L48: 400 | N48: 600 | O48: 6 | P48: 4000 | R48: 2500 | S48: =K48*L48+O48*P48+Q48*R48+M48*N48 -> 1224000 | T48: =S48*0.1 -> 122400 | U48: =S48*0.07 -> 85680 | V48: =SUM(S48:U48)*0.2 -> 286416 | W48: =SUM(S48:V48) -> 1718496 | Z48: Commercial | AA48: 3 | AB48: 2 | AC48: 1 | AD48: 3 | AE48: =IF(W48<150000,"3",IF(W48<500000,"2",IF(W48>500000,"1"))) -> 1 | AF48: 2 | AG48: 1 | AH48: 1 | AI48: {=SUM(AA48:AH48/8)} -> 1.75
B49: CP-151S | C49: TBD-05 | D49: 91st Ave SE | E49: 20th Street SE | F49: 12th Street SE | G49: TBD sidewalk along the east side of 91st Ave SE between 20th St SE and 12th St. Includes ROW and typical frontage improvements including stormwater. | S49: 2460000 | T49: 565000 | W49: =SUM(S49:V49) -> 3025000 | Z49: Commercial | AA49: 3 | AB49: 2 | AC49: 2 | AD49: 3 | AE49: =IF(W49<150000,"3",IF(W49<500000,"2",IF(W49>500000,"1"))) -> 1 | AF49: 3 | AG49: 2 | AH49: 1 | AI49: {=SUM(AA49:AH49/8)} -> 2.125
B50: CP-152S | D50: Lake Side Multi-Use Path Feasiblity Study | G50: Feasibility study/alternatives analysis for multimodal route around the lake in order to complete an active transportation route. While this is already an identified goal, this study would investigate availability and feasibility of procuring ROW along the primary road, and determine if/where alternative routes, connections, or modified designs (for example, sections of neckdowns to single vehicle lanes or sharrows where there is insufficient ROW) would be needed or recommended to complete the path. Public outreach would be an important component of the alternatives analysis. | S50: =K50*L50+O50*P50+Q50*R50+M50*N50 -> 0 | T50: =S50*0.1 -> 0 | U50: =S50*0.07 -> 0 | V50: =SUM(S50:U50)*0.2 -> 0 | W50: =SUM(S50:V50) -> 0 | AE50: =IF(W50<150000,"3",IF(W50<500000,"2",IF(W50>500000,"1"))) -> 3 | AI50: {=SUM(AA50:AH50/8)} -> 0.375
F51: Total | S51: =K51*L51+O51*P51+Q51*R51+M51*N51 -> 0 | T51: =S51*0.1 -> 0 | U51: =S51*0.07 -> 0 | V51: =SUM(S51:U51)*0.2 -> 0 | W51: =SUM(W5:W49) -> 50822692 | AE51: =IF(W51<150000,"3",IF(W51<500000,"2",IF(W51>500000,"1"))) -> 1

Sheet Roadway Projects - All
K8: Minor Arterial | L8: 3200/LF
K9: Collector | L9: 2400/LF
K10: Local Access | L10: 1600/LF
B11: Capital Facilities Plan - Roadways
B12: Project Number | C12: Project Name | D12: Description | E12: Roadway | F12: Start | G12: End | H12: Grant Award | I12: Grant Source | J12: 2022 Budget | K12: Length (LF) | L12: Cost/LF | M12: Project Planning | N12: PE | O12: ROW | P12: Construction | Q12: Contingency | R12: Total Cost | S12: Highest Land Use Type Within 1/2 Mile | T12: Roadway Type | U12: Accident Data | V12: Facility within 1/4 Mile | W12: Facility within 1/2 mile | X12: Cost | Y12: Opportunity | Z12: Grant Eligibility | AA12: Dedicated Funding | AB12: Average Score | AD12: Roadway - Evaluation Criteria
B13: RD-100 | C13: 79th Ave SE Access Road | D13: Construct new roadway including 7' bike lane, two 11' travel lanes, 5' landscape strips and 5' sidewalks for through road to Cavalero Mid-High School | E13: 79th Ave SE Access Road | F13: 20th St. NE | G13: 83rd Ave SE | K13: =1250*0.75 -> 937.5 | L13: 2400 | M13: =P13*0.01 -> 22500 | N13: =P13*0.1 -> 225000 | O13: =P13*0.07 -> 157500 | P13: =K13*L13 -> 2250000 | Q13: =SUM(M13:P13)*0.2 -> 531000 | R13: =SUM(M13:Q13) -> 3186000 | S13: 3 | T13: 2 | U13: 1 | V13: 3 | W13: 2 | X13: 2 | Y13: 3 | Z13: 3 | AA13: 3 | AB13: {=SUM(T13:AA13/9)} -> 2.1111111 | AD13: Priority | AE13: Highest Land Use Type Within 1/2 Mile | AF13: Roadway Type | AG13: Accident Data | AH13: Facility within 1/4 Mile | AI13: Facility within 1/2 mile | AJ13: Cost | AK13: Opportunity | AL13: Grant Eligibility | AM13: Dedicated Funding
B14: RD-101 | C14: Main Street Improvements (16th St NE to 20th St NE) | D14: Multi-use path, street frontage improvements along Main Street between 16th St to 20th St. | E14: Main Street | F14: 16th Street NE | G14: 20th Street NE | H14: 1959620 | I14: PSRC (Federal) | K14: 1600 | L14: 3200 | M14: =P14*0.01 -> 51200 | N14: =P14*0.1 -> 512000 | O14: =P14*0.07 -> 358400 | P14: =K14*L14 -> 5120000 | Q14: =SUM(M14:P14)*0.2 -> 1208320 | R14: =SUM(M14:Q14) -> 7249920 | S14: 3 | T14: 2 | U14: 1 | V14: 3 | W14: 2 | X14: 1 | Y14: 3 | Z14: 3 | AA14: 2 | AB14: {=SUM(T14:AA14/9)} -> 1.8888889 | AD14: High = 3 | AE14: Commercial | AF14: Minor Arterial | AG14: Fatal Accident | AH14: Adjacent to a medical office | AJ14: <$1,000,000 | AK14: Public Support is Strong | AL14: Eligible for more than two grants | AM14: Full Funding
B15: RD-113 | C15: 20th St NE and Main Street Improvements | D15: Construct roundabout and frontage improvements per the downtown subarea plan. | E15: 20th Street NE | F15: Main Street | G15: Main Street | H15: 2500000 | I15: Federal Earmark | N15: 140000 | O15: 60000 | P15: 3000000 | R15: =SUM(M15:Q15) -> 3200000 | S15: 3 | T15: 2 | U15: 1 | V15: 3 | W15: 2 | X15: 1 | Y15: 3 | Z15: 3 | AA15: 2 | AB15: {=SUM(T15:AA15/9)} -> 1.8888889 | AF15: Collisions involving pedestrians | AG15: Vehicle on Ped Accident | AH15: Adjacent to services for the disabled | AK15: Political Support is Strong
B16: RD-102I | C16: 91st Ave NE Commercial Revitalization Phase I | D16: Upgrade road to minor arterial road standard. Potential for roundabout at midblock for circulation into commercial areas. | E16: 91st Street NE | F16: Market Place | G16: SR 204 | N16: =Table3[[#This Row],[Construction]]*0.1 -> 350000 | P16: 3500000 | R16: =SUM(M16:Q16) -> 3850000 | S16: 3 | T16: 2 | U16: 3 | V16: 3 | W16: 2 | X16: 1 | Y16: 2 | Z16: 3 | AA16: 1 | AB16: {=SUM(T16:AA16/9)} -> 1.8888889 | AF16: Streets with highway interchange | AH16: Adjacent to a library
B17: RD-102II | C17: 91st Ave NE Commercial Revitalization | D17: Upgrade road to minor arterial road standard. Potential for roundabout at midblock for circulation into commercial areas. | E17: 91st Street NE | F17: SR 204 | G17: Frontier Circle | N17: =Table3[[#This Row],[Construction]]*0.1 -> 100000 | P17: 1000000 | R17: =SUM(M17:Q17) -> 1100000 | S17: 3 | T17: 2 | U17: 3 | V17: 3 | W17: 2 | X17: 1 | Y17: 2 | Z17: 3 | AA17: 1 | AB17: {=SUM(T17:AA17/9)} -> 1.8888889 | AH17: Adjacent to a senior center or senior housing
B18: RD-103 | C18: 99th Ave NE - Boulevard | D18: Upgrade road to minor arterial road standard including multi-use path or sidewalk with 7' bike lane, 11' travel lanes and 12' center lane with landscape islands. Potential for roundabout at midblock for circulation into commercial areas | E18: 99th Ave NE | F18: Market Place | G18: 4th Street NE | K18: 1300 | L18: 3200 | M18: =P18*0.01 -> 41600 | N18: =P18*0.1 -> 416000 | O18: =P18*0.07 -> 291200 | P18: =K18*L18 -> 4160000 | Q18: =SUM(M18:P18)*0.2 -> 981760 | R18: =SUM(M18:Q18) -> 5890560 | S18: 3 | T18: 2 | U18: 1 | V18: 3 | W18: 2 | X18: 1 | Y18: 1 | Z18: 3 | AA18: 1 | AB18: {=SUM(T18:AA18/9)} -> 1.5555556 | AH18: Adjacent to a school
B19: RD-104 | C19: Grade Road - Boulevard | D19: Upgrade road to minor arterial road standard including multi-use path or sidewalk with 7' bike lane, 11' travel lanes and 12' center lane with landscape islands. | E19: Grade Road | F19: Hartford | G19: Catherine Drive | K19: 3500 | L19: 3200 | M19: =P19*0.01 -> 112000 | N19: =P19*0.1 -> 1120000 | O19: =P19*0.07 -> 784000 | P19: =K19*L19 -> 11200000 | Q19: =SUM(M19:P19)*0.2 -> 2643200 | R19: =SUM(M19:Q19) -> 15859200 | S19: 3 | T19: 2 | U19: 1 | V19: 3 | W19: 2 | X19: 1 | Y19: 1 | Z19: 3 | AA19: 1 | AB19: {=SUM(T19:AA19/9)} -> 1.5555556 | AH19: Adjacent to a high use transit stop
B20: RD-105 | C20: 125th Ave NE/18th St NE/20th St NE Downtown Roadway Improvements | D20: Upgrade road to two 10' travel lanes, 8' parking on both sides, 5' planters and 5' sidewalks. | E20: 125th Ave NE/18th St NE/20th St | F20: Main Street/18th St. NE Intersection | G20: Main Street/20th St. NE Intersection | K20: 1230 | L20: 2400 | M20: =P20*0.01 -> 29520 | N20: =P20*0.1 -> 295200 | O20: =P20*0.07 -> 206640 | P20: =K20*L20 -> 2952000 | Q20: =SUM(M20:P20)*0.2 -> 696672 | R20: =SUM(M20:Q20) -> 4180032 | S20: 3 | T20: 1 | U20: 1 | V20: 3 | W20: 2 | X20: 2 | Y20: 1 | Z20: 3 | AA20: 1 | AB20: {=SUM(T20:AA20/9)} -> 1.5555556
B21: RD-106 | C21: 79th Ave SE & 8th St SE Intersection Improvements | D21: Improve the intersection at 79th Ave SE and 8th Street SE. Implement safety improvements at adjacent intersections along corridor. | E21: 79th Ave SE/8th St. SE Intersection | F21: 10th St SE | G21: 83rd Ave SE | J21: 100000 | N21: =P21*0.1 -> 50000 | O21: =P21*0.07 -> 35000 | P21: 500000 | Q21: 50000 | R21: =SUM(M21:Q21) -> 635000 | S21: 1 | T21: 2 | U21: 1 | V21: 1 | W21: 0 | X21: 3 | Y21: 3 | Z21: 2 | AA21: 1 | AB21: {=SUM(T21:AA21/9)} -> 1.4444444 | AD21: Medium = 2 | AE21: Mixed Use | AF21: Major Collector | AG21: Serious Injury Accident | AH21: Adjacent to a public office | AI21: Adjacent to a medical office | AJ21: 1,000,001- 5,000,000 | AK21: Public or Political Support Strong | AL21: Eligible for one grant | AM21: >50% Funded
B22: RD-107 | C22: Madrona Drive | D22: Convert half road to reduced standard local access road section including two 10' travel lanes and a sidewalk on a single side of the road. | E22: Madrona Drive | F22: Lake View Drive | G22: End of Road | K22: 470 | L22: 1600 | M22: =P22*0.01 -> 7520 | N22: =P22*0.1 -> 75200 | O22: =P22*0.07 -> 52640 | P22: =K22*L22 -> 752000 | Q22: =SUM(M22:P22)*0.2 -> 177472 | R22: =SUM(M22:Q22) -> 1064832 | S22: 1 | T22: 1 | U22: 1 | V22: 2 | W22: 1 | X22: 2 | Y22: 1 | Z22: 1 | AA22: 1 | AB22: {=SUM(T22:AA22/9)} -> 1.1111111 | AE22: Multi-Family | AF22: Minor Collector | AH22: Adjacent to a park | AI22: Adjacent to services to the disabled
B23: RD-108 | C23: Alder Road | D23: Convert half road to reduced standard local access road section including two 10' travel lanes and a sidewalk on a single side of the road. | E23: Alder Road | F23: Lake View Drive | G23: End of Road | K23: 700 | L23: 1600 | M23: =P23*0.01 -> 11200 | N23: =P23*0.1 -> 112000 | O23: =P23*0.07 -> 78400 | P23: =K23*L23 -> 1120000 | Q23: =SUM(M23:P23)*0.2 -> 264320 | R23: =SUM(M23:Q23) -> 1585920 | S23: 1 | T23: 1 | U23: 1 | V23: 2 | W23: 1 | X23: 2 | Y23: 1 | Z23: 1 | AA23: 1 | AB23: {=SUM(T23:AA23/9)} -> 1.1111111 | AH23: Connects or completes street(s) | AI23: Adjacent to a library
B24: RD-109 | C24: 101st Ave NE | D24: Convert half road to reduced standard local access road section including two 10' travel lanes and a sidewalk on a single side of the road. | E24: 101st Ave NE | F24: Lundeen Parkway | G24: 30th Street NE | K24: 2100 | L24: 1600 | M24: =P24*0.01 -> 33600 | N24: =P24*0.1 -> 336000 | O24: =P24*0.07 -> 235200 | P24: =K24*L24 -> 3360000 | Q24: =SUM(M24:P24)*0.2 -> 792960 | R24: =SUM(M24:Q24) -> 4757760 | S24: 1 | T24: 1 | U24: 1 | V24: 2 | W24: 1 | X24: 2 | Y24: 1 | Z24: 1 | AA24: 1 | AB24: {=SUM(T24:AA24/9)} -> 1.1111111 | AI24: Adjacent to a senior center or senior housing
B25: RD-110 | C25: 99th/20th U-turn Channelization | D25: Rechannelize 20th Street SE to allow for U-turns at the intersection of 20th Street SE and 99th Ave SE. | E25: 20th Street SE | F25: 99th Ave SE | G25: 99th Ave SE | J25: 30000 | K25: 100 | L25: 0 | N25: 5000 | P25: 25000 | R25: =SUM(M25:Q25) -> 30000 | S25: 3 | T25: 3 | U25: 3 | V25: 2 | W25: 1 | X25: 3 | Y25: 3 | Z25: 1 | AA25: 3 | AB25: {=SUM(T25:AA25/9)} -> 2.1111111 | AI25: Adjacent to a school
B26: RD-111 | C26: 12th St. SE/87th Ave SE Road Realignment | D26: The intersection at 87th Street SE and 12th Street SE is not aligned to provide adequate sight distances for vehicles. Project will realign the intersection and construct additional roadway surface. | J26: 50000 | K26: 200 | L26: 1600 | M26: =P26*0.01 -> 3200 | N26: 10000 | O26: =P26*0.07 -> 22400 | P26: =Table3[[#This Row],[Length (LF)]]*Table3[[#This Row],[Cost/LF]] -> 320000 | Q26: =SUM(M26:P26)*0.2 -> 71120 | R26: =SUM(M26:Q26) -> 426720 | S26: 1 | T26: 1 | U26: 1 | V26: 1 | W26: 1 | X26: 3 | Y26: 3 | Z26: 1 | AA26: 3 | AB26: {=SUM(T26:AA26/9)} -> 1.5555556
B27: RD-112 | C27: 91st Ave SE/24th Street SE/S. Lake Stevens Road | D27: Construction of minor arterial south of 20th Street SE that provides an additional connection to SR 9. | E27: 91st Ave SE | F27: 24th St. SE | G27: 20th St. SE | H27: 3000000 | I27: TIB | J27: 15500000 | R27: =SUM(M27:Q27) -> 0 | S27: 3 | T27: 3 | U27: 1 | V27: 2 | W27: 1 | X27: 1 | Y27: 3 | Z27: 3 | AA27: 3 | AB27: {=SUM(T27:AA27/9)} -> 1.8888889 | AD27: Low = 1 | AE27: Single Family | AF27: Neighborhood | AG27: Other | AI27: Adjacent to a high use transit stop | AJ27: >5,000,001 | AK27: Support Not Known/Not Supportive | AL27: Not eligible for grants | AM27: <50% Funded
B28: RD-113 | C28: Mill Spur Traffic Calming | D28: A study and implementation of traffic calming at Mill Spur
B29: RD-114 | C29: Lundeen Parkway Splitter Island Concrete Replacement | D29: The rock-lined approaches at the Lundeen Parkway roundabouts requires that the PW crew perform regular and time-consuming maintenances to ensure weeds do not grow.
B30: RD-115 | C30: Replace Speed Feedback Signs | D30: Current speed feedback signs in the City are not supported from the manufacture and the majority of them are failing and need to be replaced. Speed feedback signs have been proven to help reduce traffic speeds.
B31: RD-116 | C31: EDDS Update | D31: Update Chapter 5-9 and publish
B32: RD-117 | C32: Traffic Safety Cameras Program and Equipment | D32: City Council has authorized the ordinance to install traffic safety cameras. This ordinance grants the ability to put into place a program. The budget request reflects the need to do a traffic analysis in the City in the locations proposed to install the cameras. This budget amount also includes the installation of the cameras. _x000D_ _x000D_ Each camera is approximately $65,000 per camera. The goal is to install 2 cameras each in 3 locations. The additional budget will cover consultant costs to perform the traffic analysis and justification required to install the cameras.
D33: Total | R33: =SUM(R13:R27) -> 53015944 | AE33: Industrial | AI33: Adjacent to a public office
AI34: Adjacent to a park
AI35: Connects or completes street(s)
AD37: Adjacent is within 1/4 mile

Sheet Parks - All
B2: Capital Facilities Plan - Parks | AB2: Parks - Scoring Criteria
A3: Project Number | B3: Project Number2 | C3: Project Name | D3: Location | E3: Description | F3: Grant Award | G3: Grant Source | H3: 2022 Budget | I3: Construction Estimate | J3: A&E | K3: ROW/Property | L3: Contingency | M3: Construction Management | N3: Total Cost | O3: Zoning | P3: Zoning Score | Q3: Park Service Type/ Classification | R3: Park Distribution | S3: Park Amenities | T3: Cost | U3: Opportunity | V3: Partnership Opportunity | W3: Grant Eligibility | X3: Dedicated Funding | Y3: Average Score | AB3: Priority | AC3: Zoning | AD3: Park Service Type/Classification | AE3: Park Distribution | AF3: Park Amenities | AG3: Cost | AH3: Opportunity | AI3: Partnership Opportunity | AJ3: Grant Eligibility | AK3: Dedicated Funding
B4: PR-100 | C4: Frontier Heights Phase II | D4: 48.005875, -122.111164 | E4: Design and construction of a multiuse athletic field, drainage and parking lot improvements and pickleball courts. | F4: 0 | G4: WWRP ($500K), YAF ($350K) | H4: 225000 | I4: 3040314 | J4: =I4*0.1 -> 304031.4 | K4: 0 | L4: =SUM(I4*0.1) -> 304031.4 | M4: =I4*0.07 -> 212821.98 | N4: =SUM(I4:M4) -> 3861198.8 | O4: Public/Semi-Public | P4: 3 | Q4: 3 | R4: 3 | S4: 3 | T4: =IF(N4<150000,"3",IF(N4<500000,"2",IF(N4>500000,"1"))) -> 1 | U4: 3 | V4: 2 | W4: 3 | X4: 2 | Y4: =SUM(P4:X4)/8 -> 2.75 | AB4: High = 3 | AC4: Multi-Family | AD4: Community Park (>10 acres) | AE4: Community park that fills 2.5 mile distribution gap to residential zone | AF4: Playfields | AG4: <$150,000 | AH4: Public Support is Strong and Political Support is Strong | AI4: Agreement in place | AJ4: Eligible for more than two grants | AK4: Full Funding
B5: PR-101 | C5: Mill Spur Concession/Restroom | E5: Construct a restroom and concession building on Mill Spur | H5: 200000 | I5: 180000 | J5: =I5*0.1 -> 18000 | L5: =SUM(I5*0.1) -> 18000 | M5: =I5*0.07 -> 12600 | N5: =SUM(I5:M5) -> 228600 | O5: Public/Semi-Public | P5: 3 | Q5: 2 | R5: 3 | S5: 3 | T5: =IF(N5<150000,"3",IF(N5<500000,"2",IF(N5>500000,"1"))) -> 2 | U5: 3 | V5: 3 | W5: 3 | X5: 2 | Y5: =SUM(P5:X5)/8 -> 2.75 | AD5: Trail >1 Mile | AE5: Neighborhood park that fills 1 mile distribution gap to residential zone | AF5: Community Center
B6: PR-102 | C6: Eagle Ridge Park Phase II | D6: 48.018446, -122.106445 | E6: Design and construct an amphitheater, playground, restrooms, parking and frontage improvements. | F6: 428000 | G6: RCO | H6: 995200 | I6: 3200000 | J6: 500000 | K6: 0 | L6: =SUM(I6*0.1) -> 320000 | M6: =I6*0.07 -> 224000 | N6: =SUM(I6:M6) -> 4244000 | O6: Public/Semi-Public | P6: 2 | Q6: 3 | R6: 3 | S6: 3 | T6: =IF(N6<150000,"3",IF(N6<500000,"2",IF(N6>500000,"1"))) -> 1 | U6: 3 | V6: 2 | W6: 3 | X6: 2 | Y6: =SUM(P6:X6)/8 -> 2.625 | AC6: Mixed Use | AE6: Mini-park that fills 0.5 mile distribution gap to residential areas | AF6: Playgrounds and Restroom
B7: PR-103 | C7: North Cove Dock Boat Slips | E7: Add up to six boat slips to the west side of the pier. | F7: 116245 | G7: RCO | H7: =F7 -> 116245 | I7: 100000 | J7: =I7*0.1 -> 10000 | K7: =I7*0.07 -> 7000 | L7: =SUM(I7*0.1) -> 10000 | M7: =I7*0.07 -> 7000 | N7: =SUM(I7:M7) -> 134000 | O7: Multi Family | P7: 3 | Q7: 2 | R7: 3 | S7: 3 | T7: =IF(N7<150000,"3",IF(N7<500000,"2",IF(N7>500000,"1"))) -> 3 | U7: 3 | V7: 2 | W7: 2 | X7: 3 | Y7: =SUM(P7:X7)/8 -> 2.625 | AF7: Dock/Pier and Swim Beach
B8: PR-104 | C8: Cedarwood Recreation Center | E8: Construct a community center/recreation space by renovating an existing building that previously served this purpose. | H8: 100000 | I8: 4950000 | J8: 1031073 | K8: 340000 | L8: =SUM(I8*0.1) -> 495000 | M8: =I8*0.07 -> 346500 | N8: =SUM(I8:M8) -> 7162573 | O8: Public/Semi-Public | P8: 3 | Q8: 3 | R8: 2 | S8: 3 | T8: =IF(N8<150000,"3",IF(N8<500000,"2",IF(N8>500000,"1"))) -> 1 | U8: 3 | V8: 3 | W8: 2 | X8: 1 | Y8: =SUM(P8:X8)/8 -> 2.5
B9: PR-105 | C9: North Cove Pedestrian Bridge | E9: Construct abutments and place previously purchased pedestrian bridge over the Lake Stevens outlet channel between North Cove Park and North Lakeshore Drive. | H9: 50000 | I9: 50000 | J9: =I9*0.1 -> 5000 | K9: =I9*0.07 -> 3500 | L9: =SUM(I9*0.1) -> 5000 | M9: =I9*0.07 -> 3500 | N9: =SUM(I9:M9) -> 67000 | O9: Commercial | P9: 1 | Q9: 2 | R9: 3 | S9: 3 | T9: =IF(N9<150000,"3",IF(N9<500000,"2",IF(N9>500000,"1"))) -> 3 | U9: 1 | V9: 3 | W9: 3 | X9: 2 | Y9: =SUM(P9:X9)/8 -> 2.25
B10: PR-106 | C10: Sunset Park Phase II | E10: Pave parking lot, drainage improvements, ADA path with overlook deck. | G10: RCO (Pending) | H10: 0 | I10: 0 | J10: =I10*0.1 -> 0 | K10: 0 | L10: =SUM(I10*0.1) -> 0 | M10: =I10*0.07 -> 0 | N10: =SUM(I10:M10) -> 0 | O10: Single Family | P10: 2 | Q10: 1 | R10: 3 | S10: 3 | T10: =IF(N10<150000,"3",IF(N10<500000,"2",IF(N10>500000,"1"))) -> 3 | U10: 3 | V10: 3 | W10: 2 | X10: 2 | Y10: =SUM(P10:X10)/8 -> 2.375
B11: PR-107 | C11: North Cove Docks @ Boat Launch | E11: Repair/Replace boat launch dock and slips. | H11: 0 | I11: 2300000 | J11: =I11*0.1 -> 230000 | K11: 0 | L11: =SUM(I11*0.1) -> 230000 | M11: =I11*0.07 -> 161000 | N11: =SUM(I11:M11) -> 2921000 | O11: Commercial | P11: 1 | Q11: 2 | R11: 3 | S11: 3 | T11: =IF(N11<150000,"3",IF(N11<500000,"2",IF(N11>500000,"1"))) -> 1 | U11: 3 | V11: 3 | W11: 3 | X11: 1 | Y11: =SUM(P11:X11)/8 -> 2.375
B12: PR-108 | C12: Frontier Heights Phase III | D12: 48.005875, -122.111164 | E12: Construction of a labyrinth exercise equipment and a sensory garden with associated pedestrian connections. | H12: 0 | I12: 150000 | J12: =I12*0.1 -> 15000 | K12: 0 | L12: =SUM(I12*0.1) -> 15000 | M12: =I12*0.07 -> 10500 | N12: =SUM(I12:M12) -> 190500 | O12: Public/Semi-Public | P12: 3 | Q12: 3 | R12: 3 | S12: 3 | T12: =IF(N12<150000,"3",IF(N12<500000,"2",IF(N12>500000,"1"))) -> 2 | U12: 3 | V12: 1 | W12: 1 | X12: 1 | Y12: =SUM(P12:X12)/8 -> 2.25 | AB12: Medium = 2 | AC12: Single Family | AD12: Neighborhood Park (<10 acres) | AE12: Community park that fills <2.5 mile to 1 mile distribution gap | AF12: Trail/Pathway (>0.5 miles) | AG12: $150,001 to $500,000 | AH12: Public or Political Support Strong | AI12: Agreement is pending with support | AJ12: Eligible for one grant | AK12: >50% Funded
B13: PR-109 | C13: 20th St. SE Ballfields/Powerline Trail Phase I | D13: 47.979151, -122.113690 | E13: Construct paved parking lot adjacent to 20th Street SE and 3,800 linear feet of multi-use path between 20th Street SE and 8th Street SE. | G13: Pandemic Recovery (500K), Park Mitigation (1.1 million) | H13: 475000 | I13: =125000+3800*(300) -> 1265000 | J13: =I13*0.1 -> 126500 | K13: =I13*0.01 -> 12650 | L13: =SUM(I13*0.12) -> 151800 | M13: =I13*0.07 -> 88550 | N13: =SUM(I13:M13) -> 1644500 | O13: Single Family | P13: 2 | Q13: 2 | R13: 3 | S13: 3 | T13: =IF(N13<150000,"3",IF(N13<500000,"2",IF(N13>500000,"1"))) -> 1 | U13: 2 | V13: 2 | W13: 2 | X13: 2 | Y13: =SUM(P13:X13)/8 -> 2.25 | AD13: Trail >0.5 Mile | AE13: Neighborhood park that fills <1 to 0.5 mile distribution gap to residential zone
B14: PR-110 | C14: Eagle Ridge Property Acquisition | E14: Acquire residential property adjacent to Eagle Ridge Park | H14: 0 | I14: 150000 | J14: 45000 | K14: 700000 | L14: =SUM(I14*0.1) -> 15000 | M14: =I14*0.07 -> 10500 | N14: =SUM(I14:M14) -> 920500 | O14: Single Family | P14: 2 | Q14: 3 | R14: 3 | S14: 3 | T14: =IF(N14<150000,"3",IF(N14<500000,"2",IF(N14>500000,"1"))) -> 1 | U14: 3 | V14: 2 | W14: 1 | X14: 1 | Y14: =SUM(P14:X14)/8 -> 2.25 | AF14: Swim Beach
B15: PR-111 | C15: Sunset Park Phase I | E15: Stabilize dock and shoreline. Improve landscaping. | F15: 5000 | G15: County Grant | H15: 0 | I15: 0 | J15: 0 | L15: =SUM(I15*0.1) -> 0 | M15: =I15*0.07 -> 0 | N15: =SUM(I15:M15) -> 0 | O15: Single Family | P15: 2 | Q15: 1 | R15: 3 | S15: 3 | T15: =IF(N15<150000,"3",IF(N15<500000,"2",IF(N15>500000,"1"))) -> 3 | U15: 3 | V15: 3 | W15: 1 | X15: 1 | Y15: =SUM(P15:X15)/8 -> 2.125
B16: PR-112 | C16: Neighborhood Park Acquisition | D16: Varies | E16: Identify locations for and acquire lands for a neighborhood level park in the southeastern part of the City. | H16: 0 | I16: 750000 | J16: =I16*0.1 -> 75000 | K16: 1000000 | L16: =SUM(I16*0.1) -> 75000 | M16: =I16*0.07 -> 52500 | N16: =SUM(I16:M16) -> 1952500 | O16: Public/Semi-Public | P16: 2 | Q16: 2 | R16: 3 | S16: 3 | T16: =IF(N16<150000,"3",IF(N16<500000,"2",IF(N16>500000,"1"))) -> 1 | U16: 3 | V16: 1 | W16: 2 | X16: 1 | Y16: =SUM(P16:X16)/8 -> 2.125 | AB16: Low = 1 | AC16: Commercial | AD16: Mini-Park (<1 acre) | AE16: Community park that fills <1 mile distribution gap | AF16: View Corridor | AG16: >$500,000 | AH16: Support Not Known/Not Supportive | AI16: No agreement in place or pending | AJ16: Eligibility Unknown | AK16: <50% Funded
B17: PR-113 | C17: Davies Beach Pier Restoration | E17: Restore the pier with new decking, piling repairs as needed, add three boat slips with lifts for emergency responder boats. Pier area is 5,500 sq. ft. | H17: 50000 | I17: 280000 | J17: =I17*0.1 -> 28000 | K17: =I17*0.07 -> 19600 | L17: =SUM(I17*0.1) -> 28000 | M17: =I17*0.07 -> 19600 | N17: =SUM(I17:M17) -> 375200 | O17: Public/Semi-Public | P17: 2 | Q17: 2 | R17: 2 | S17: 3 | T17: =IF(N17<150000,"3",IF(N17<500000,"2",IF(N17>500000,"1"))) -> 2 | U17: 2 | V17: 3 | W17: 1 | X17: 1 | Y17: =SUM(P17:X17)/8 -> 2 | AC17: Industrial | AD17: Open Space | AE17: Neighborhood park that fills <0.5 mile distribution gap to residential zone | AF17: Open Space
B18: PR-114 | C18: Future - Pump Track and Climbing Wall | E18: Improve trails, construct a pump track and climbing walls. | G18: Park Mitigation | H18: 25000 | I18: 1000000 | J18: =I18*0.1 -> 100000 | K18: =I18*0.07 -> 70000 | L18: =SUM(I18*0.1) -> 100000 | M18: =I18*0.07 -> 70000 | N18: =SUM(I18:M18) -> 1340000 | O18: Public/Semi-Public | P18: 2 | Q18: 2 | R18: 3 | S18: 2 | T18: =IF(N18<150000,"3",IF(N18<500000,"2",IF(N18>500000,"1"))) -> 1 | U18: 3 | V18: 1 | W18: 2 | X18: 1 | Y18: =SUM(P18:X18)/8 -> 2 | AD18: Trail <0.5 Mile | AE18: Mini-park that fills <0.5 mile distribution gap to residential areas | AF18: Trail/Pathway (<0.5 miles)
B19: PR-115 | C19: Bayview Trail Phase 2 | E19: Construct 4,000 linear feet of multi-use path between 8th St. SE and Market Place. | H19: 0 | I19: =300*3800 -> 1140000 | J19: =I19*0.1 -> 114000 | K19: 50000 | L19: =SUM(I19*0.1) -> 114000 | M19: =I19*0.07 -> 79800 | N19: =SUM(I19:M19) -> 1497800 | O19: Multi Family | P19: 3 | Q19: 3 | R19: 1 | S19: 2 | T19: =IF(N19<150000,"3",IF(N19<500000,"2",IF(N19>500000,"1"))) -> 1 | U19: 2 | V19: 1 | W19: 1 | X19: 1 | Y19: =SUM(P19:X19)/8 -> 1.75
B20: PR-116 | C20: Bonneville Ballfields | E20: Replace the field surface and renovate the athletic field amenities. | F20: - | H20: 0 | I20: 750000 | J20: =I20*0.1 -> 75000 | K20: 0 | L20: =SUM(I20*0.1) -> 75000 | M20: =I20*0.07 -> 52500 | N20: =SUM(I20:M20) -> 952500 | O20: Single Family | P20: 2 | Q20: 2 | R20: 2 | S20: 3 | T20: =IF(N20<150000,"3",IF(N20<500000,"2",IF(N20>500000,"1"))) -> 1 | U20: 1 | V20: 1 | W20: 1 | X20: 1 | Y20: =SUM(P20:X20)/8 -> 1.625
B21: PR-117 | C21: Mini-Park Restoration | E21: Restoration program for mini-parks throughout the City. Mini-parks typically have playgrounds that need to be replaced or repaired. This is recurring annual funding. | I21: 75000 | J21: =I21*0.1 -> 7500 | K21: 0 | L21: =SUM(I21*0.1) -> 7500 | M21: =I21*0.07 -> 5250 | N21: =SUM(I21:M21) -> 95250 | O21: Public/Semi-Public | P21: 2 | Q21: 1 | R21: 2 | S21: 3 | T21: =IF(N21<150000,"3",IF(N21<500000,"2",IF(N21>500000,"1"))) -> 3 | U21: 2 | V21: 1 | W21: 1 | X21: 1 | Y21: =SUM(P21:X21)/8 -> 1.625
B22: R-1148 | C22: North Cove Parking Lot | E22: Remove administrative buildings and construct new parking lot. | I22: 450000 | J22: =I22*0.1 -> 45000 | L22: =SUM(I22*0.1) -> 45000 | M22: =I22*0.07 -> 31500 | N22: =SUM(I22:M22) -> 571500 | O22: Public/Semi-Public | T22: =IF(N22<150000,"3",IF(N22<500000,"2",IF(N22>500000,"1"))) -> 1 | Y22: =SUM(P22:X22)/8 -> 0
B23: R-119 | C23: Bayview Trail Phase 1a | E23: Construct 1,000 linear feet of multi-use trail from 12th St. SE and 8th St. SE | J23: =I23*0.1 -> 0 | L23: =SUM(I23*0.1) -> 0 | M23: =I23*0.07 -> 0 | N23: 400000 | O23: Public/Semi-Public | T23: =IF(N23<150000,"3",IF(N23<500000,"2",IF(N23>500000,"1"))) -> 2 | Y23: =SUM(P23:X23)/8 -> 0
B24: R-120 | C24: Bayview Trail Phase 3 | E24: Construct 3200 linear feet of multi-use trail from Market Place to Frontier CIrcle | I24: 1000000 | J24: 100000 | K24: 200000 | L24: =SUM(I24*0.1) -> 100000 | M24: =I24*0.07 -> 70000 | N24: =SUM(I24:M24) -> 1470000 | T24: =IF(N24<150000,"3",IF(N24<500000,"2",IF(N24>500000,"1"))) -> 1
B25: R-121 | C25: NC Playground Concrete Seat Wall Adjustment | E25: This project consists of hiring a contractor to cut a portion of the vertical concrete wall and patching the ground around it. | J25: =I25*0.1 -> 0 | L25: =SUM(I25*0.1) -> 0 | M25: =I25*0.07 -> 0 | N25: =SUM(I25:M25) -> 0 | T25: =IF(N25<150000,"3",IF(N25<500000,"2",IF(N25>500000,"1"))) -> 3 | Y25: =SUM(P25:X25)/8 -> 0
B26: R-122 | C26: WeatherTrak Irrigation System Addition | E26: 4 parks - North Cove, Davies, Lundeen and Oak. This is a smart irrigation controller that uses weather data to adjust watering schedules | J26: =I26*0.1 -> 0 | L26: =SUM(I26*0.1) -> 0 | M26: =I26*0.07 -> 0 | N26: =SUM(I26:M26) -> 0 | T26: =IF(N26<150000,"3",IF(N26<500000,"2",IF(N26>500000,"1"))) -> 3 | Y26: =SUM(P26:X26)/8 -> 0
B27: R-123 | C27: Extend Railing - NC Observation Deck | E27: The North Cove Observation Deck has a railing with cable system around half of it. A step will be added to the west side (grass hill) of the observation deck and continue the fencing around the North side of the Observation Deck. | J27: =I27*0.1 -> 0 | L27: =SUM(I27*0.1) -> 0 | M27: =I27*0.07 -> 0 | N27: =SUM(I27:M27) -> 0 | T27: =IF(N27<150000,"3",IF(N27<500000,"2",IF(N27>500000,"1"))) -> 3 | Y27: =SUM(P27:X27)/8 -> 0
B28: R-124 | C28: Utility/Storage Building - Cavalero | E28: A 10x20 concrete block building at Cavalero Park for storage of materials and supplies needed for parks maintenance | J28: =I28*0.1 -> 0 | L28: =SUM(I28*0.1) -> 0 | M28: =I28*0.07 -> 0 | N28: =SUM(I28:M28) -> 0 | T28: =IF(N28<150000,"3",IF(N28<500000,"2",IF(N28>500000,"1"))) -> 3 | Y28: =SUM(P28:X28)/8 -> 0
B29: R-125 | C29: Cavalero Community/Sports Center - Design | E29: Design and Engineering. 80-100k Community & Sports Center - Partnership with TBD | J29: =I29*0.1 -> 0 | L29: =SUM(I29*0.1) -> 0 | M29: =I29*0.07 -> 0 | N29: =SUM(I29:M29) -> 0 | T29: =IF(N29<150000,"3",IF(N29<500000,"2",IF(N29>500000,"1"))) -> 3 | Y29: =SUM(P29:X29)/8 -> 0
B30: R-126 | C30: Cavalero Community/Sports Center - Design | E30: Design and Engineering. 80-100k Community & Sports Center - Partnership with TBD | J30: =I30*0.1 -> 0 | L30: =SUM(I30*0.1) -> 0 | M30: =I30*0.07 -> 0 | N30: =SUM(I30:M30) -> 0 | T30: =IF(N30<150000,"3",IF(N30<500000,"2",IF(N30>500000,"1"))) -> 3 | Y30: =SUM(P30:X30)/8 -> 0
B31: R-127 | C31: Water Deduct Meter Installation | E31: Irrigation or water lines may need to be modified to reroute water. Each deduct meter will cost approximately $1300 to purchase, staff will install. | J31: =I31*0.1 -> 0 | L31: =SUM(I31*0.1) -> 0 | M31: =I31*0.07 -> 0 | N31: =SUM(I31:M31) -> 0 | T31: =IF(N31<150000,"3",IF(N31<500000,"2",IF(N31>500000,"1"))) -> 3 | Y31: =SUM(P31:X31)/8 -> 0
B32: R-128 | C32: Security Cameras - Cavalero | E32: Security cameras for Cavalero Park. | J32: =I32*0.1 -> 0 | L32: =SUM(I32*0.1) -> 0 | M32: =I32*0.07 -> 0 | N32: =SUM(I32:M32) -> 0 | T32: =IF(N32<150000,"3",IF(N32<500000,"2",IF(N32>500000,"1"))) -> 3 | Y32: =SUM(P32:X32)/8 -> 0
B33: R-129 | C33: Monument/Entrance Sign - Cavalero | E33: The City will be acquiring Cavalero Park from the County. This park will need a City entry sign to match our standards, which consists of a base and blue sign displaying the park name and address. | J33: =I33*0.1 -> 0 | L33: =SUM(I33*0.1) -> 0 | M33: =I33*0.07 -> 0 | N33: =SUM(I33:M33) -> 0 | T33: =IF(N33<150000,"3",IF(N33<500000,"2",IF(N33>500000,"1"))) -> 3 | Y33: =SUM(P33:X33)/8 -> 0
B34: R-130 | C34: North Cove Parking Lot & Recreation Building Design | E34: Design and Engineering. Remove one of the administrative buildings, repurpose the other and construct new parking lot | J34: =I34*0.1 -> 0 | L34: =SUM(I34*0.1) -> 0 | M34: =I34*0.07 -> 0 | N34: =SUM(I34:M34) -> 0 | T34: =IF(N34<150000,"3",IF(N34<500000,"2",IF(N34>500000,"1"))) -> 3 | Y34: =SUM(P34:X34)/8 -> 0
J35: =I35*0.1 -> 0 | L35: =SUM(I35*0.1) -> 0 | M35: =I35*0.07 -> 0 | N35: =SUM(I35:M35) -> 0 | T35: =IF(N35<150000,"3",IF(N35<500000,"2",IF(N35>500000,"1"))) -> 3 | Y35: =SUM(P35:X35)/8 -> 0
J36: =I36*0.1 -> 0 | L36: =SUM(I36*0.1) -> 0 | M36: =I36*0.07 -> 0 | N36: =SUM(I36:M36) -> 0 | T36: =IF(N36<150000,"3",IF(N36<500000,"2",IF(N36>500000,"1"))) -> 3 | Y36: =SUM(P36:X36)/8 -> 0
J37: =I37*0.1 -> 0 | L37: =SUM(I37*0.1) -> 0 | M37: =I37*0.07 -> 0 | N37: =SUM(I37:M37) -> 0 | T37: =IF(N37<150000,"3",IF(N37<500000,"2",IF(N37>500000,"1"))) -> 3 | Y37: =SUM(P37:X37)/8 -> 0
J38: =I38*0.1 -> 0 | L38: =SUM(I38*0.1) -> 0 | M38: =I38*0.07 -> 0 | N38: =SUM(I38:M38) -> 0 | T38: =IF(N38<150000,"3",IF(N38<500000,"2",IF(N38>500000,"1"))) -> 3 | Y38: =SUM(P38:X38)/8 -> 0
J39: =I39*0.1 -> 0 | L39: =SUM(I39*0.1) -> 0 | M39: =I39*0.07 -> 0 | N39: =SUM(I39:M39) -> 0 | T39: =IF(N39<150000,"3",IF(N39<500000,"2",IF(N39>500000,"1"))) -> 3 | Y39: =SUM(P39:X39)/8 -> 0
J40: =I40*0.1 -> 0 | L40: =SUM(I40*0.1) -> 0 | M40: =I40*0.07 -> 0 | N40: =SUM(I40:M40) -> 0 | T40: =IF(N40<150000,"3",IF(N40<500000,"2",IF(N40>500000,"1"))) -> 3 | Y40: =SUM(P40:X40)/8 -> 0
J41: =I41*0.1 -> 0 | L41: =SUM(I41*0.1) -> 0 | M41: =I41*0.07 -> 0 | N41: =SUM(I41:M41) -> 0 | T41: =IF(N41<150000,"3",IF(N41<500000,"2",IF(N41>500000,"1"))) -> 3 | Y41: =SUM(P41:X41)/8 -> 0

Sheet Surface Water
A2: Capital Facilities Plan - Stormwater
A3: Project Number | B3: Project Name | C3: Location | D3: Description | E3: 2022 Budget | F3: Construction Estimate | G3: A&E | H3: ROW/Property | I3: Contingency | J3: Construction Management | K3: Total Cost | L3: Land Use | M3: Flood Mitigation Benefit/Risk Mitigation | N3: Environmental/ Sustainability | O3: Operational/ Budget Impact | P3: Cost | Q3: Opportunity | R3: Partnership Opportunity | S3: Grant Eligibility | T3: Dedicated Funding | U3: Average Score | W3: Surface Water - Scoring Criteria
A4: SW-105 | B4: 20th Street NE Culvert Replacement/Channel realignment | D4: Phase II - Downtown Flood Mitigation: Replacement of the 20th Street NE culvert with a bridge to reduce the severity and occurrence of flooding in the downtown area. This project includes channel realignment. | F4: 3200000 | G4: =F4*0.1 -> 320000 | H4: 100000 | I4: =SUM(F4*0.1) -> 320000 | J4: =F4*0.07 -> 224000 | K4: =SUM(F4:J4) -> 4164000 | L4: 3 | M4: 3 | N4: 3 | O4: 3 | P4: 1 | Q4: 3 | R4: 2 | S4: 2 | T4: 1 | U4: =SUM(L4:T4)/6 -> 3.5 | W4: Priority | X4: Land Use | Y4: Flood Mitigation Benefit/Risk Mitigation | Z4: Environmental/ Sustainability | AA4: Operational/ Budget Impact | AB4: Cost | AC4: Opportunity | AD4: Partnership Opportunity | AE4: Grant Eligibility | AF4: Dedicated Funding
A5: SW-106 | B5: Hartford Crossing - New and Channel realignment | D5: Phase III - Downtown Flood Mitigation: Replacement of two culverts on Hartford Drive with bridges and channel restoration through the wetland west of Hartford. | F5: 5500000 | G5: =F5*0.1 -> 550000 | H5: 10000 | I5: =SUM(F5*0.1) -> 550000 | J5: =F5*0.07 -> 385000 | K5: =SUM(F5:J5) -> 6995000 | L5: 3 | M5: 3 | N5: 3 | O5: 3 | P5: 1 | Q5: 3 | R5: 2 | S5: 2 | T5: 1 | U5: =SUM(L5:T5)/6 -> 3.5 | W5: High = 3 | X5: Commercial | Y5: >5 Structures Mitigated | Z5: Total Fish Barrier Restored | AA5: Substantial reduction in operational costs | AB5: <$150,000 | AC5: Public Support is Strong and Political Support is Strong | AD5: Agreement in place | AE5: Eligible for more than two grants | AF5: Full Funding
A6: SW-101 | B6: Weir Replacement | D6: Phase I - Downtown Flood Mitigation: Replacement of the weir at the outlet of Lake Stevens with a control structure that provides fish passage and automated control of the lake level. | E6: 75000 | F6: 750000 | G6: =F6*0.1 -> 75000 | H6: 0 | I6: =SUM(F6*0.1) -> 75000 | J6: =F6*0.07 -> 52500 | K6: =SUM(F6:J6) -> 952500 | L6: 3 | M6: 3 | N6: 3 | O6: 3 | P6: 1 | Q6: 3 | R6: 3 | S6: 1 | T6: 1 | U6: =SUM(L6:T6)/6 -> 3.5 | X6: Industrial | Y6: Minor Arterial | Z6: Stream Daylighted | AA6: Substantial reduction in financial risk | AD6: Infrastructure will be damaged if project is ont constructed
A7: SW-107 | B7: 18th Street NE Culvert Replacement/ realignment | D7: Phase IV - Downtown Flood Mitigation: Replacement of the 18th Street NE with a bridge. | F7: 1000000 | G7: =F7*0.1 -> 100000 | I7: =SUM(F7*0.1) -> 100000 | J7: =F7*0.07 -> 70000 | K7: =SUM(F7:J7) -> 1270000 | L7: 3 | M7: 3 | N7: 3 | O7: 3 | P7: 1 | Q7: 2 | R7: 2 | S7: 2 | T7: 1 | U7: =SUM(L7:T7)/6 -> 3.3333333 | Y7: Sole Access | Z7: Project Improves TMDL
A8: SW-104 | B8: Bridge 06 Replacement - 36th Street NE | D8: Bridge 06 requires a quarterly inspection due to structural concerns. This bridge should be replaced to ensure commercial traffic can access the Hartford Industrial area of the City. | F8: 2500000 | G8: =F8*0.1 -> 250000 | I8: =SUM(F8*0.1) -> 250000 | J8: =F8*0.07 -> 175000 | K8: =SUM(F8:J8) -> 3175000 | L8: 3 | M8: 3 | N8: 1 | O8: 3 | P8: 1 | Q8: 3 | R8: 1 | S8: 2 | T8: 1 | U8: =SUM(L8:T8)/6 -> 3
A9: SW-109 | B9: Regional Stormwater Facility Downtown | D9: Construct a regional stormwater facility in downtown Lake Stevens to encourage commercial growth. | F9: 1000000 | G9: =F9*0.1 -> 100000 | I9: =SUM(F9*0.1) -> 100000 | J9: =F9*0.07 -> 70000 | K9: =SUM(F9:J9) -> 1270000 | L9: 3 | M9: 2 | N9: 2 | O9: 2 | P9: 1 | Q9: 2 | R9: 2 | S9: 1 | T9: 1 | U9: =SUM(L9:T9)/6 -> 2.6666667
A10: SW-110 | B10: Regional Stormwater Facility Hartford Industrial | D10: Construct a regional stormwater facility in adjacent to Hartford Drive to encourage industrial growth. | F10: 1000000 | G10: =F10*0.1 -> 100000 | I10: =SUM(F10*0.1) -> 100000 | J10: =F10*0.07 -> 70000 | K10: =SUM(F10:J10) -> 1270000 | L10: 3 | M10: 2 | N10: 2 | O10: 2 | P10: 1 | Q10: 2 | R10: 2 | S10: 1 | T10: 1 | U10: =SUM(L10:T10)/6 -> 2.6666667
A11: SW-111 | B11: Catherine Creek/Hartford Crossing Replacement | F11: 2500000 | G11: =F11*0.1 -> 250000 | I11: =SUM(F11*0.1) -> 250000 | J11: =F11*0.07 -> 175000 | K11: =SUM(Table6[[#This Row],[Construction Estimate]:[Construction Management]]) -> 3175000 | L11: 3 | M11: 1 | N11: 2 | O11: 1 | P11: 1 | Q11: 3 | R11: 1 | S11: 3 | T11: 1 | U11: =SUM(L11:T11)/6 -> 2.6666667
A12: Sur | B12: 36th Street Culvert Replacement - Fish Passable | D12: Replace the culvert at 36th Street NE that conveys a tributary to Catherine Creek. | E12: 0 | F12: 600000 | G12: =F12*0.1 -> 60000 | I12: =SUM(F12*0.1) -> 60000 | J12: =F12*0.07 -> 42000 | K12: =SUM(F12:J12) -> 762000 | L12: 3 | M12: 2 | N12: 2 | O12: 1 | P12: 1 | Q12: 2 | R12: 2 | S12: 2 | T12: 1 | U12: =SUM(L12:T12)/6 -> 2.6666667
A13: SW-102 | B13: 10th/79th Storm Line Replacement | D13: Replacement of inadequately sized stormwater pipes and structures with structures/pipes to convey the significant quantity of water in this area. | E13: 100000 | F13: 400000 | G13: =F13*0.1 -> 40000 | I13: =SUM(F13*0.1) -> 40000 | J13: =F13*0.07 -> 28000 | K13: =SUM(F13:J13) -> 508000 | L13: 1 | M13: 2 | N13: 3 | O13: 3 | P13: 1 | Q13: 2 | R13: 1 | S13: 1 | T13: 1 | U13: =SUM(L13:T13)/6 -> 2.5
A14: SW-103 | B14: 99th Ave SE/4th St. SE Culvert Feasibility | D14: Design/feasibility of a culvert replacement project at 99th Ave SE/4th St. SE. | E14: 75000 | F14: 1500000 | G14: =F14*0.1 -> 150000 | I14: =SUM(F14*0.1) -> 150000 | J14: =F14*0.07 -> 105000 | K14: =SUM(F14:J14) -> 1905000 | L14: 1 | M14: 1 | N14: 1 | O14: 1 | P14: 1 | Q14: 1 | R14: 1 | S14: 1 | T14: 1 | U14: =SUM(L14:T14)/6 -> 1.5 | W14: Medium = 2 | X14: Multi-Family | Y14: >3 Structures Mitigated | Z14: Partial Fish Barrier Restored | AA14: Moderate reduction in operational costs | AB14: $150,001 to $500,000 | AC14: Public or Political Support Strong | AD14: Agreement is pending with support | AE14: Eligible for one grant | AF14: >50% Funded
A15: SW-112 | B15: SWM Fee - Rate Study and Fee Adoption | D15: This project is to hire a consultant to set surface water utility rates. Assess the stormwater management fee structure to ensure fair distribution of costs, compliance with regulations, and financial sustainability. This study should include staff needs, NPDES requirements, integrate actions from the basins plan, EMP, SMAP, and CCTV projects. The surface water utility fees have been set through 2027. The last rate study for the City took place in 2018. Since 2018, the City has inspected and inventoried all stormwater facility assets, set condition ratings for more than half of the stormwater conveyance infrastructure, identified capital projects, and completed long-range plan to address water quality by assessing enhanced maintenance standards, retrofits to existing infrastructure, and new capital projects. All of this information will be used in a new study to set utility rates. | G15: =F15*0.1 -> 0 | I15: =SUM(F15*0.1) -> 0 | J15: =F15*0.07 -> 0 | K15: =SUM(F15:J15) -> 0 | U15: =SUM(L15:T15)/6 -> 0
D16: Total | G16: =F16*0.1 -> 0 | I16: =SUM(F16*0.1) -> 0 | J16: =F16*0.07 -> 0 | K16: =SUM(K4:K14) -> 25446500 | Y16: Major/Minor Collector | Z16: Restoration of Wetlands/Wetland reconnection | AA16: Moderate reduction in financial risk | AD16: Infrastructure impacts are likely.
Z17: Improves Water Quality
W19: Low = 1 | X19: Single Family | Y19: <2 Structures Mitigated | Z19: No Fish Barrier Restored | AA19: Minor operational cost reduction | AB19: >$500,000 | AC19: Support Not Known/Not Supportive | AD19: No agreement in place or pending | AE19: Eligibility Unknown | AF19: <50% Funded
Y20: Neighborhood Roadway | Z20: No Wetland Reconnection | AA20: Minor financial risk reduction | AD20: Impacts are unknown.
Z21: No Water Quality Improvement

Sheet Facilities
A2: Capital Facilities Plan - Facilities
A3: Project Number | B3: Project Name | C3: Location | D3: Description | E3: Grant Award | F3: Grant Source | G3: 2022 Budget | H3: Construction Estimate | I3: A&E | J3: ROW/Property | K3: Contingency | L3: Construction Management | M3: Total Cost | N3: Critical Facility | O3: Operational/ Budget Impact | P3: Environmental/ Sustainability | Q3: Public Health and Safety | R3: Cost | S3: Opportunity | T3: Partnership Opportunity | U3: Grant Eligibility | V3: Dedicated Funding | W3: Average Score | Y3: Facilities - Scoring Criteria
A4: FC-111 | B4: Additional PW Shop Building Feasibility/Preliminary Design | D4: Prepare feasibility report and preliminary design for additional public works shop building at current shop location. | I4: 30000 | K4: =SUM(H4*0.1) -> 0 | L4: =H4*0.07 -> 0 | M4: =SUM(H4:L4) -> 30000 | N4: 3 | O4: 3 | P4: 3 | Q4: 2 | R4: 3 | S4: 3 | T4: 3 | U4: 1 | V4: 1 | W4: =SUM(N4:V4)/9 -> 2.4444444 | Y4: Priority | Z4: Critical Facility | AA4: Operational/ Budget Impact | AB4: Environmental/ Sustainability | AC4: Public Health and Safety | AD4: Cost | AE4: Opportunity | AF4: Partnership Opportunity | AG4: Grant Eligibility | AH4: Dedicated Funding
A5: FC-103 | B5: Police Station HVAC | D5: LSPD facility was purchased in 2019 and remodeled. The life span on the current HVAC and air conditioning units have met their lifespan and are failing in the Administration/Operations Building. The training center systems were replaced shortly after occupancy. Project includes four AC units and four furnaces. | H5: 50000 | I5: =H5*0.1 -> 5000 | K5: =SUM(H5*0.1) -> 5000 | L5: =H5*0.07 -> 3500 | M5: =SUM(H5:L5) -> 63500 | N5: 3 | O5: 2 | P5: 3 | Q5: 3 | R5: 3 | S5: 2 | T5: 1 | U5: 1 | V5: 1 | W5: =SUM(N5:V5)/9 -> 2.1111111 | Y5: High = 3 | Z5: Police Station | AA5: Reduces debt service and operational costs | AB5: Reduces utility costs and improves energy/resource consumption. | AC5: Significantly improves the public health and safety | AD5: <$150,000 | AE5: Public Support is Strong and Political Support is Strong | AF5: Agreement in place | AG5: Eligible for more than two grants | AH5: Full Funding
A6: FC-109 | B6: Refueling Station Cover and Structure | D6: Construct a ~1,200 square foot roof/cover structure over the refueling station at the PW Shop. This is a requirement of the City's NPDES permit. | H6: =1200*30 -> 36000 | I6: =H6*0.1 -> 3600 | K6: =SUM(H6*0.1) -> 3600 | L6: =H6*0.07 -> 2520 | M6: =SUM(H6:L6) -> 45720 | N6: 3 | O6: 3 | P6: 3 | Q6: 2 | R6: 3 | S6: 2 | T6: 1 | U6: 1 | V6: 1 | W6: =SUM(N6:V6)/9 -> 2.1111111 | Z6: City Hall | AB6: Reduces reliance on fossil fuels. | AC6: Improves employee public health and safety.
A7: FC-110 | B7: Decant Facility and PW Yard Materials Storage Bins Cover | D7: Construct roof/cover structures over the four materials bins at the public works yard and four bins at the decant facility. Total area to cover is 4,700 square feet. | H7: =4700*12 -> 56400 | I7: =H7*0.1 -> 5640 | K7: =SUM(H7*0.1) -> 5640 | L7: =H7*0.07 -> 3948 | M7: =SUM(H7:L7) -> 71628 | N7: 3 | O7: 3 | P7: 3 | Q7: 2 | R7: 3 | S7: 2 | T7: 1 | U7: 1 | V7: 1 | W7: =SUM(N7:V7)/9 -> 2.1111111 | Z7: Public Works Shop | AB7: Reduces use of hazardous materials.
A8: FC-108 | B8: Security Cameras | D8: Procure and install cameras on municipal facilities to improve security. | H8: 50000 | I8: =H8*0.1 -> 5000 | K8: =SUM(H8*0.1) -> 5000 | L8: =H8*0.07 -> 3500 | M8: =SUM(H8:L8) -> 63500 | N8: 3 | O8: 2 | P8: 1 | Q8: 3 | R8: 3 | S8: 3 | T8: 1 | U8: 1 | V8: 1 | W8: =SUM(N8:V8)/9 -> 2
A9: FC-112 | B9: 131st Ave NE Sewer Extension | D9: Construct ~550 linear feet of sewer main beneath 131st Ave NE and connect public works shop to public sewer. Costs will be shared with the Lake Stevens Sewer District. This cost estimate is 50% share. | H9: =580*720/2 -> 208800 | I9: =H9*0.1 -> 20880 | K9: =SUM(H9*0.1) -> 20880 | L9: =H9*0.07 -> 14616 | M9: =SUM(H9:L9) -> 265176 | N9: 3 | O9: 2 | P9: 3 | Q9: 2 | R9: 1 | S9: 3 | T9: 2 | U9: 1 | V9: 1 | W9: =SUM(N9:V9)/9 -> 2
A10: FC-114 | B10: Machias Sewer Connection | D10: Construct ~480 linear feet of sewer main along City property, between 131st Ave NE and Machias Rd. | H10: =480*720 -> 345600 | I10: =H10*0.1 -> 34560 | K10: =SUM(H10*0.1) -> 34560 | L10: =H10*0.07 -> 24192 | M10: =SUM(H10:L10) -> 438912 | W10: =SUM(N10:V10)/9 -> 0
A11: FC-102 | B11: City Hall | D11: Relocate City Hall from North Cove Park to an alternative location | H11: 1000000 | I11: =H11*0.1 -> 100000 | J11: 9000000 | K11: =SUM(H11*0.1) -> 100000 | L11: =H11*0.07 -> 70000 | M11: =SUM(H11:L11) -> 10270000 | N11: 3 | O11: 2 | P11: 2 | Q11: 3 | R11: 1 | S11: 3 | T11: 1 | U11: 1 | V11: 1 | W11: =SUM(N11:V11)/9 -> 1.8888889
A12: FC-104 | B12: Library HVAC and Paint | D12: Replace the HVAC system and paint the city-owned building that is occupied by Sno-Isle Library. | H12: 70000 | I12: =H12*0.1 -> 7000 | K12: =SUM(H12*0.1) -> 7000 | L12: =H12*0.07 -> 4900 | M12: =SUM(H12:L12) -> 88900 | N12: 2 | O12: 2 | P12: 3 | Q12: 2 | R12: 3 | S12: 2 | T12: 1 | U12: 1 | V12: 1 | W12: =SUM(N12:V12)/9 -> 1.8888889
A13: FC-101 | B13: Museum | D13: Design and construct a museum building on Mill Spur adjacent to the Grimm House. | E13: 0 | F13: Museum Grant ($744K), Mill Spur Property Sale ($500K), ARPA ($656K) | G13: 0 | H13: 1900000 | I13: =H13*0.1 -> 190000 | K13: =SUM(H13*0.1) -> 190000 | L13: =H13*0.07 -> 133000 | M13: =SUM(H13:L13) -> 2413000 | N13: 2 | O13: 1 | P13: 1 | Q13: 1 | R13: 1 | S13: 3 | T13: 2 | U13: 3 | V13: 2 | W13: =SUM(N13:V13)/9 -> 1.7777778
A14: FC-105 | B14: Eagle Ridge Storage Building | D14: Restore/remodel the storage facility at Eagle Ridge Park for use by the Parks Department. | H14: 100000 | I14: =H14*0.1 -> 10000 | K14: =SUM(H14*0.1) -> 10000 | L14: =H14*0.07 -> 7000 | M14: =SUM(H14:L14) -> 127000 | N14: 2 | O14: 2 | P14: 2 | Q14: 2 | R14: 2 | S14: 2 | T14: 1 | U14: 2 | V14: 1 | W14: =SUM(N14:V14)/9 -> 1.7777778 | Y14: Medium = 2 | Z14: Other Government Buildings | AA14: Reduces debt service or operating costs | AB14: Reduces vehicle trips | AC14: Moderate improvement to public health/safety | AD14: $150,001 to $500,000 | AE14: Public or Political Support Strong | AF14: Agreement is pending with support | AG14: Eligible for one grant | AH14: >50% Funded
A15: FC-106 | B15: Lundeen Park Recreation Building Remodel | D15: Remodel the Lundeen Park recreation building for use by vendors and the Parks Department. This project includes security and IT upgrades. | H15: 100000 | I15: =H15*0.1 -> 10000 | K15: =SUM(H15*0.1) -> 10000 | L15: =H15*0.07 -> 7000 | M15: =SUM(H15:L15) -> 127000 | N15: 2 | O15: 2 | P15: 2 | Q15: 2 | R15: 2 | S15: 2 | T15: 1 | U15: 2 | V15: 1 | W15: =SUM(N15:V15)/9 -> 1.7777778 | AB15: Reduces Energy Consumption | AC15: Moderate improvement to employee health/safety
A16: FC-113 | B16: Mill Spur Downtown Parking Lot | D16: The city has identified potential parking locations in downtown Lake Stevens. Public parking is a goal of the downtown Lake Stevens Subarea Plan. The first site is designed and will be ready to construct in 2023. The second location is dependent on coordination and an agreement with the property owner. | H16: 120000 | I16: 20000 | K16: =SUM(H16*0.1) -> 12000 | L16: =H16*0.07 -> 8400 | M16: =SUM(H16:L16) -> 160400 | N16: 1 | O16: 2 | P16: 2 | Q16: 2 | R16: 2 | S16: 3 | T16: 2 | U16: 1 | V16: 1 | W16: =SUM(N16:V16)/9 -> 1.7777778
A17: FC-115 | B17: Water Main Extension - 20th Street SE between 91st Street SE and 79th Street SE | D17: Installation of ~4,000 linear feet water main on the south side of 20th Street SE providing water service for commercial and residental customers. Water main will reduce roadway cuts across recently improved road. 2023 funding will be used for feasibility. | I17: 100000 | K17: =SUM(H17*0.1) -> 0 | L17: =H17*0.07 -> 0 | M17: =SUM(H17:L17) -> 100000 | N17: 1 | O17: 1 | P17: 3 | Q17: 3 | R17: 1 | S17: 3 | T17: 2 | U17: 1 | V17: 1 | W17: =SUM(N17:V17)/9 -> 1.7777778
A18: FC-107 | B18: 1819 South Lake Stevens Road - Commercial Building Paint and Remodel | D18: Paint the exterior of the building. Minor remodel of the building including replacement/repair of aging HVAC system and other appliances. This project includes replacement of the eastern fire escape stairway. | H18: 40000 | I18: =H18*0.1 -> 4000 | K18: =SUM(H18*0.1) -> 4000 | L18: =H18*0.07 -> 2800 | M18: =SUM(H18:L18) -> 50800 | N18: 1 | O18: 1 | P18: 2 | Q18: 1 | R18: 3 | S18: 2 | T18: 1 | U18: 1 | V18: 1 | W18: =SUM(N18:V18)/9 -> 1.4444444 | AB18: Improves well-being of employees
A19: FC-116 | B19: AC Register in Chief's conference room | D19: AC Register in Chief's conference room. When the door is closed the room temperature increases quickly about 20 degrees and is VERY uncomfortable. | K19: =SUM(H19*0.1) -> 0 | L19: =H19*0.07 -> 0 | M19: =SUM(H19:L19) -> 0 | W19: =SUM(N19:V19)/9 -> 0
A20: FC-117 | B20: Flagpole Landscaping | D20: Flagpole Landscaping to increase the beautification of the flagpole area for ceremonial events and recgonition. | K20: =SUM(H20*0.1) -> 0 | L20: =H20*0.07 -> 0 | M20: =SUM(H20:L20) -> 0 | W20: =SUM(N20:V20)/9 -> 0
A21: FC-118 | B21: FOB reader on pedestrian gate | D21: FOB reader on pedestrian gate to access the PD training room and parking lot from walking path between buildings | K21: =SUM(H21*0.1) -> 0 | L21: =H21*0.07 -> 0 | M21: =SUM(H21:L21) -> 0 | W21: =SUM(N21:V21)/9 -> 0
A22: FC-119 | B22: 2nd Story to training center for additional office space | D22: 2nd Story to training center for additional office space - 2035 This is for future growth and expansion. PW director provided prelimenary discussion | K22: =SUM(H22*0.1) -> 0 | L22: =H22*0.07 -> 0 | M22: =SUM(H22:L22) -> 0 | W22: =SUM(N22:V22)/9 -> 0
D23: Total | K23: =SUM(H23*0.1) -> 0 | L23: =H23*0.07 -> 0 | M23: =SUM(M4:M18) -> 14315536
Y24: Low = 1 | Z24: Non-Government Buildings | AA24: No effect on debt service or operating costs | AB24: No known environment/ sustainability benefit | AC24: No known benefit | AD24: >$500,000 | AE24: Support Not Known/Not Supportive | AF24: No agreement in place or pending | AG24: Eligibility Unknown | AH24: <50% Funded

Sheet TBD Projects
F3: Date: | G3: 44782
F4: Prepared by: | G4: Aaron Halverson, Public Works Director
B5: Transportation Benefit District (TBD) Projects
B6: Roadway Projects
B7: Project | C7: Description | D7: Primary Road | E7: Start | F7: End | G7: Cost Estimate
B8: 79th Ave SE Access Road | C8: Construct new roadway including 7' bike lane, two 11' travel lanes, 5' landscape strips and 5' sidewalks for through road to Cavalero Mid-High School | D8: 79th Ave SE Access Road | E8: 20th Street SE | F8: 83rd Ave SE | G8: ='Roadway Projects - All'!R13 -> 3186000
B9: Main Street Redevelopment | C9: Multi-use path, street frontage improvements and roundabout at Main Street & 20th St NE intersection. | D9: Main Street | E9: 16th Street NE | F9: 20th Street NE | G9: ='Roadway Projects - All'!R18 -> 5890560
B10: 91st Ave NE Commercial Revitalization | C10: Upgrade road to minor arterial road standard including multi-use path or sidewalk with 7' bike lane, 11' travel lanes and 12' center lane with landscape islands. Potential for roundabout at midblock for circulation into commercial areas | D10: 91st Street NE | E10: Market Place | F10: SR 204 | G10: ='Roadway Projects - All'!R17 -> 1100000
B11: 99th Ave NE Redevelopment | C11: Upgrade road to minor arterial road standard including multi-use path or sidewalk with 7' bike lane, 11' travel lanes and 12' center lane with landscape islands. Potential for roundabout at midblock for circulation into commercial areas | D11: 99th Ave NE | E11: Market Place | F11: 4th Street NE | G11: ='Roadway Projects - All'!R20 -> 4180032
B12: Pavement Preservation | C12: Maintain existing roadways to 80% pavement condition rating. | D12: Annual Expense | G12: 800000
F13: Total | G13: =SUM(G8:G12) -> 15156592
B14: Sidewalk Projects
B15: Project | C15: Description | D15: Primary Road | E15: Start | F15: End | G15: Cost Estimate
B16: 91st Street SE - School Sidewalk Connections | C16: Construct 5,000 linear feet of sidewalk with landscape strip buffer, install 18 ADA compliant ramps and install lighted crosswalk signs on 91st Street SE from 20th Street SE to Market Street. There are three schools in the project area and several sections without sidewalks or compliant ADA ramps. | D16: 91st Street SE | E16: 20th Street SE | F16: Market Street | G16: =SUM('Sidewalk Projects - All'!W6,'Sidewalk Projects - All'!W7,'Sidewalk Projects - All'!#REF!,'Sidewalk Projects - All'!W9) -> #REF!
B17: 16th Street NE Centennial Trail Connector | C17: Construct 1,900 linear feet of multi-use path and 4 ADA compliance ramps on 16th Street NE between Main Street and the Centennial Trail. This will complete the bicycle and pedestrian connection from the Centennial Trail at Hartford Drive, through downtown Lake Stevens, back to the Centennial Trail. | D17: 16th Street NE | E17: Main Street | F17: Centennial Trial | G17: ='Sidewalk Projects - All'!W5 -> 4470000
B18: North Lakeshore Swim Beach Connection to Downtown | C18: Construct a sidewalk on North Lakeshore Drive between downtown Lake Stevens and North Lake Shore Swim Beach. | D18: North Lakeshore Drive | E18: Main Street | F18: North Lakeshore Swim Beach | G18: =SUM('Sidewalk Projects - All'!W10,'Sidewalk Projects - All'!W21) -> 1061424
B19: 117th Street NE - High School Sidewalk Connection | C19: Construct 2,100 linear feet of sidewalks and 8 ADA compliant ramps on 117th Street NE between 20th Street NE and 26th Street NE. | D19: 117th Street NE | E19: 20th Street NE | F19: 26th Street NE | G19: ='Sidewalk Projects - All'!W8 -> 383292
B20: Soper Hill Road Pedestrian Connection to Lundeen Parkway | C20: Construct 3,000 linear feet of sidewalk, 4 ADA compliant ramps and two lighted crosswalk signs on Soper Hill Road from Lundeen Parkway to SR 9. This project will connect pedestrians from Lundeen Parkway to Eagle Ridge Park, the Senior Center and the Soper Hill Commercial area. | D20: Soper Hill Road | E20: Lundeen Parkway | F20: SR9 | G20: ='Sidewalk Projects - All'!W11 -> 1460000
B21: 99th Ave NE - Sunnycrest Elementary to 30th St. NE | C21: Construct 1,300 linear feet of sidewalk and two ADA compliant ramps between Sunnycrest Elementary south and 30th St. NE. This project will provide pedestrian access between the residential areas to the south and the school. | D21: 99th Ave NE | E21: Sunnycrest Elementary | F21: 30th Street NE | G21: ='Sidewalk Projects - All'!W22 -> 746928
B22: 79th Ave SE - Sidewalk Connections | C22: Connect several sections of sidewalks on 79th Street SE between 8th Street SE and 20th Street SE. | D22: 79th Street SE | E22: 20th Street SE | F22: 8th Street SE | G22: =SUM('Sidewalk Projects - All'!W34,'Sidewalk Projects - All'!W35,'Sidewalk Projects - All'!W27,) -> 3071888
F23: Total | G23: =SUM(G16:G22) -> #REF!

Sheet School Sidewalks (Draft)
R4: Evaluation Criteria
R5: 5 - State Route | S5: 5 - (0-0.25 Miles) | T5: 5 -Commercial/Mixed Use | U5: 5 - 1,251 | V5: 5 - <100,000 | W5: 5 - Full Funding
R6: 4 - Minor Arterial | S6: 4 - (0.25-0.5 Miles) | T6: 4 - Mixed Use | U6: 4 - 1001 to 1,250 | V6: 4 - 100,001 to 500,000 | W6: 4 - 75-99%
R7: 3 - Major Collector | S7: 3 - (0.5-1 Miles) | T7: 3 - Multi Family | U7: 3 - 751 to 1000 | V7: 3 - 500,001 to 750,000 | W7: 3 - 50-74%
R8: 2 - Minor Collector | S8: 2 - (1-1.5 Miles) | T8: 2 - Single Family | U8: 2 - 501 to 750 | V8: 2 - 750,001 to 1,000,000 | W8: 2 - 25-49%
R9: 1 - Neighborhood | S9: 1 - (1.5-2 Miles) | T9: 1 - Industrial | U9: 1 - 0 to 500 | V9: 1 - 1,000,001 to 1,500,000 | W9: 1 - 0-24%
C10: Lake Stevens - School Sidewalk Project Analysis
B11: Project Number | C11: Roadway | D11: Start | E11: End | F11: Nearest School | G11: Number of Students | H11: Sidewalk Length | I11: Cost/LF | J11: Ramps | K11: Cost/Ea | L11: RRFB | M11: Cost/Ea | N11: Const. Estimate | O11: Engineering | P11: ROW | Q11: Total Cost | R11: Roadway Classification | S11: Proximity to School | T11: Highest Land Use Type Within 0.5 Miles | U11: Number of Students | V11: Cost | W11: Dedicated Funding | X11: Average Score
C12: 79th Ave SE | D12: 12th Street SE | E12: 8th Street SE | F12: Cavalero Mid High School | G12: 1444 | H12: 1300 | I12: 400 | J12: 2 | K12: 4000 | M12: 2500 | N12: =H12*I12+J12*K12+L12*M12 -> 528000 | O12: =N12*0.1 -> 52800 | P12: =N12*0.07 -> 36960 | Q12: =SUM(N12:P12) -> 617760 | R12: 3 | S12: 3 | T12: 5 | U12: 5 | V12: 3 | W12: 0 | X12: {=SUM(R12:W12/6)} -> 3.1666667
C13: 83rd Ave SE | D13: 20th Street SE | E13: 17th Street SE | F13: Cavalero Mid High School | G13: 1444 | H13: 850 | I13: 400 | K13: 4000 | M13: 2500 | N13: =H13*I13+J13*K13+L13*M13 -> 340000 | O13: =N13*0.1 -> 34000 | P13: =N13*0.07 -> 23800 | Q13: =SUM(N13:P13) -> 397800 | R13: 3 | S13: 4 | T13: 5 | U13: 5 | V13: 4 | W13: 0 | X13: {=SUM(R13:W13/6)} -> 3.5
C14: 103rd Ave SE | D14: SR 9 | E14: Glenwood Elementary | F14: Glennwood Elementary | G14: 554 | H14: 0 | I14: 400 | J14: 12 | K14: 4000 | L14: 4 | M14: 2500 | N14: =H14*I14+J14*K14+L14*M14 -> 58000 | O14: =N14*0.1 -> 5800 | P14: =N14*0.07 -> 4060 | Q14: =SUM(N14:P14) -> 67860 | R14: 3 | S14: 5 | T14: 5 | U14: 2 | V14: 5 | W14: 0 | X14: {=SUM(R14:W14/6)} -> 3.3333333
C15: 20th Street SE | D15: S. Lake Stevens Road | E15: 113th Drive SE | F15: Glennwood Elementary | G15: 554 | H15: 2700 | I15: 400 | J15: 6 | K15: 4000 | L15: 0 | M15: 2500 | N15: =H15*I15+J15*K15+L15*M15 -> 1104000 | O15: =N15*0.1 -> 110400 | P15: =N15*0.07 -> 77280 | Q15: =SUM(N15:P15) -> 1291680 | R15: 4 | S15: 5 | T15: 5 | U15: 2 | V15: 1 | W15: 0 | X15: {=SUM(R15:W15/6)} -> 2.8333333
B16: CP-104 | C16: 113th Ave NE | D16: 32nd Street NE | E16: 36th Street NE | F16: Highland Elementary School | G16: 578 | H16: 0 | I16: 400 | J16: 11 | K16: 4000 | L16: 2 | M16: 2500 | N16: =H16*I16+J16*K16+L16*M16 -> 49000 | O16: =N16*0.1 -> 4900 | P16: =N16*0.07 -> 3430 | Q16: =SUM(N16:P16) -> 57330 | R16: 1 | S16: 5 | T16: 5 | U16: 2 | V16: 5 | W16: 0 | X16: {=SUM(R16:W16/6)} -> 3
C17: Cedar Road | D17: 20th St. NE | E17: 30th Street NE | F17: Highland Elementary School | G17: 578 | H17: 3400 | I17: 400 | J17: 6 | K17: 4000 | L17: 2 | M17: 2500 | N17: =H17*I17+J17*K17+L17*M17 -> 1389000 | O17: =N17*0.1 -> 138900 | P17: =N17*0.07 -> 97230 | Q17: =SUM(N17:P17) -> 1625130 | R17: 1 | S17: 4 | T17: 1 | U17: 2 | V17: 1 | W17: 0 | X17: {=SUM(R17:W17/6)} -> 1.5
B18: CP-123 | C18: 91st Ave SE | D18: 4th St. SE | E18: Market Street | F18: Hillcrest Elementary School/Lake Stevens Middle School/Skyline Elementary | G18: 2048 | H18: 1000 | I18: 400 | J18: 8 | K18: 4000 | M18: 2500 | N18: =H18*I18+J18*K18+L18*M18 -> 432000 | O18: =N18*0.1 -> 43200 | P18: =N18*0.07 -> 30240 | Q18: =SUM(N18:P18) -> 505440 | R18: 3 | S18: 5 | T18: 5 | U18: 5 | V18: 3 | W18: 0 | X18: {=SUM(R18:W18/6)} -> 3.5
B19: CP-107 | C19: 91st Ave SE | D19: 12th Place SE | E19: 20th Street SE | F19: Hillcrest Elementary School/Lake Stevens Middle School/Skyline Elementary | G19: 2048 | H19: 2400 | I19: 400 | J19: 5 | K19: 4000 | M19: 2500 | N19: =H19*I19+J19*K19+L19*M19 -> 980000 | O19: =N19*0.1 -> 98000 | P19: =N19*0.07 -> 68600 | Q19: =SUM(N19:P19) -> 1146600 | R19: 3 | S19: 5 | T19: 5 | U19: 5 | V19: 1 | W19: 0 | X19: {=SUM(R19:W19/6)} -> 3.1666667
C20: 91st Ave SE | D20: 8th Street SE | E20: 4th Street SE | F20: Hillcrest Elementary School/Lake Stevens Middle School/Skyline Elementary | G20: 2048 | H20: 1350 | I20: 400 | J20: 4 | K20: 4000 | M20: 2500 | N20: =H20*I20+J20*K20+L20*M20 -> 556000 | O20: =N20*0.1 -> 55600 | P20: =N20*0.07 -> 38920 | Q20: =SUM(N20:P20) -> 650520 | R20: 3 | S20: 5 | T20: 1 | U20: 5 | V20: 3 | W20: 0 | X20: {=SUM(R20:W20/6)} -> 2.8333333
C21: 8th Street SE | D21: 79th Ave SE | E21: 91st Avenue SE | F21: Hillcrest Elementary School/Lake Stevens Middle School/Skyline Elementary | G21: 2048 | H21: 2500 | I21: 400 | J21: 4 | K21: 4000 | L21: 2 | M21: 2500 | N21: =H21*I21+J21*K21+L21*M21 -> 1021000 | O21: =N21*0.1 -> 102100 | P21: =N21*0.07 -> 71470 | Q21: =SUM(N21:P21) -> 1194570 | R21: 3 | S21: 4 | T21: 1 | U21: 5 | V21: 1 | W21: 0 | X21: {=SUM(R21:W21/6)} -> 2.3333333
C22: 117th Street NE | D22: 20th Street NE | E22: 26th Street NE | F22: Lake Stevens High School | G22: 1691 | H22: 2100 | I22: 400 | J22: 8 | K22: 4000 | M22: 2500 | N22: =H22*I22+J22*K22+L22*M22 -> 872000 | O22: =N22*0.1 -> 87200 | P22: =N22*0.07 -> 61040 | Q22: =SUM(N22:P22) -> 1020240 | R22: 3 | S22: 4 | T22: 1 | U22: 5 | V22: 1 | W22: 5 | X22: {=SUM(R22:W22/6)} -> 3.1666667
B23: CP-128S | C23: 20th Street NE | D23: Main Street | E23: 131st Ave SE | F23: Mt. Pilchuck Elementary | G23: 551 | H23: 0 | I23: 400 | J23: 4 | K23: 4000 | L23: 2 | M23: 2500 | N23: =H23*I23+J23*K23+L23*M23 -> 21000 | O23: =N23*0.1 -> 2100 | P23: =N23*0.07 -> 1470 | Q23: =SUM(N23:P23) -> 24570 | R23: 4 | S23: 5 | T23: 5 | U23: 2 | V23: 5 | W23: 0 | X23: {=SUM(R23:W23/6)} -> 3.5
B24: CP-102 | C24: 131st Ave NE | D24: 20th Street NE | E24: Hartford Road | F24: Mt. Pilchuck Elementary | G24: 551 | H24: 1800 | I24: 400 | J24: 2 | K24: 4000 | L24: 2 | M24: 2500 | N24: =H24*I24+J24*K24+L24*M24 -> 733000 | O24: =N24*0.1 -> 73300 | P24: =N24*0.07 -> 51310 | Q24: =SUM(N24:P24) -> 857610 | R24: 1 | S24: 5 | T24: 5 | U24: 2 | V24: 5 | W24: 0 | X24: {=SUM(R24:W24/6)} -> 3
B25: CP-111 | C25: Grade Road | D25: 22nd Street NE | E25: Lake Stevens Library | F25: North Lake Middle School | G25: 648 | H25: 160 | I25: 400 | J25: 2 | K25: 4000 | L25: 2 | M25: 2500 | N25: =H25*I25+J25*K25+L25*M25 -> 77000 | O25: =N25*0.1 -> 7700 | P25: =N25*0.07 -> 5390 | Q25: =SUM(N25:P25) -> 90090 | R25: 3 | S25: 5 | T25: 5 | U25: 2 | V25: 5 | W25: 0 | X25: {=SUM(R25:W25/6)} -> 3.3333333
B26: CP-112 | C26: 123rd Avenue NE | D26: North Lakeshore Drive | E26: 22nd Street NE | F26: North Lake Middle School | G26: 648 | H26: 650 | I26: 400 | J26: 10 | K26: 4000 | M26: 2500 | N26: =H26*I26+J26*K26+L26*M26 -> 300000 | O26: =N26*0.1 -> 30000 | P26: =N26*0.07 -> 21000 | Q26: =SUM(N26:P26) -> 351000 | R26: 1 | S26: 5 | T26: 5 | U26: 2 | V26: 4 | W26: 0 | X26: {=SUM(R26:W26/6)} -> 2.8333333
C27: Lake View Drive | D27: Lundeen Parkway | E27: 29th Street NE | F27: Stevens Creek Elementary | G27: 619 | H27: 1500 | I27: 400 | J27: 2 | K27: 4000 | L27: 0 | M27: 2500 | N27: =H27*I27+J27*K27+L27*M27 -> 608000 | O27: =N27*0.1 -> 60800 | P27: =N27*0.07 -> 42560 | Q27: =SUM(N27:P27) -> 711360 | R27: 1 | S27: 5 | T27: 5 | U27: 2 | V27: 3 | W27: 0 | X27: {=SUM(R27:W27/6)} -> 2.6666667
C28: Soper Hill Road | D28: Lake Drive | E28: SR 9 | F28: Stevens Creek Elementary | G28: 619 | H28: 3000 | I28: 400 | J28: 4 | K28: 4000 | L28: 2 | M28: 2500 | N28: =H28*I28+J28*K28+L28*M28 -> 1221000 | O28: =N28*0.1 -> 122100 | P28: =N28*0.07 -> 85470 | Q28: =SUM(N28:P28) -> 1428570 | R28: 4 | S28: 4 | T28: 5 | U28: 2 | V28: 1 | W28: 0 | X28: {=SUM(R28:W28/6)} -> 2.6666667
C29: 99th Ave NE | D29: Sunnycrest Elem. | E29: 30th Street NE | F29: Sunnycrest Elementary | G29: 631 | H29: 1300 | I29: 400 | J29: 2 | K29: 4000 | M29: 2500 | N29: =H29*I29+J29*K29+L29*M29 -> 528000 | O29: =N29*0.1 -> 52800 | P29: =N29*0.07 -> 36960 | Q29: =SUM(N29:P29) -> 617760 | R29: 3 | S29: 5 | T29: 1 | U29: 2 | V29: 3 | W29: 0 | X29: {=SUM(R29:W29/6)} -> 2.3333333
C30: 30th Street NE | D30: 99th Ave NE | E30: Callow Road | F30: Sunnycrest Elementary | G30: 631 | H30: 1200 | I30: 400 | J30: 4 | K30: 4000 | L30: 2 | M30: 2500 | N30: =H30*I30+J30*K30+L30*M30 -> 501000 | O30: =N30*0.1 -> 50100 | P30: =N30*0.07 -> 35070 | Q30: =SUM(N30:P30) -> 586170 | R30: 1 | S30: 4 | T30: 1 | U30: 2 | V30: 3 | W30: 0 | X30: {=SUM(R30:W30/6)} -> 1.8333333

Sheet TBD by Allocation (Draft)
B1: TBD Analysis
C2: Survey Response Share | D2: Revenue Projection (Sales Tax) | N2: Total
D3: 2023 | E3: 2024 | F3: 2025 | G3: 2026 | H3: 2027 | I3: 2028 | J3: 2029 | K3: 2030 | L3: 2031 | M3: 2032
D4: 1500000 | E4: =D4*1.045 -> 1567500 | F4: =E4*1.045 -> 1638037.5 | G4: =F4*1.045 -> 1711749.2 | H4: =G4*1.03 -> 1763101.7 | I4: =H4*1.03 -> 1815994.7 | J4: =I4*1.03 -> 1870474.6 | K4: =J4*1.03 -> 1926588.8 | L4: =K4*1.03 -> 1984386.5 | M4: =L4*1.03 -> 2043918
C5: Overlays | D5: 500000 | E5: 500000 | F5: 500000 | G5: 500000 | H5: 500000 | I5: 500000 | J5: 500000 | K5: 500000 | L5: 500000 | M5: 500000
D6: =D4-D5 -> 1000000 | E6: =E4-E5 -> 1067500 | F6: =F4-F5 -> 1138037.5 | G6: =G4-G5 -> 1211749.2 | H6: =H4-H5 -> 1263101.7 | I6: =I4-I5 -> 1315994.7 | J6: =J4-J5 -> 1370474.6 | K6: =K4-K5 -> 1426588.8 | ... M6: =M4-M5 -> 1543918
B7: Sidewalk | C7: 0.52 | D7: =D6*$C$7 -> 520000 | E7: =E6*$C$7 -> 555100 | F7: =F6*$C$7 -> 591779.5 | G7: =G6*$C$7 -> 630109.58 | H7: =H6*$C$7 -> 656812.86 | I7: =I6*$C$7 -> 684317.25 | J7: =J6*$C$7 -> 712646.77 | K7: =K6*$C$7 -> 741826.17 | ... M7: =M6*$C$7 -> 802837.39 | N7: =SUM(D7:M7) -> 6667310.5
B8: Street/Road | C8: 0.37 | D8: =D6*$C$8 -> 370000 | E8: =E6*$C$8 -> 394975 | F8: =F6*$C$8 -> 421073.88 | G8: =G6*$C$8 -> 448347.2 | H8: =H6*$C$8 -> 467347.62 | I8: =I6*$C$8 -> 486918.04 | J8: =J6*$C$8 -> 507075.59 | K8: =K6*$C$8 -> 527837.85 | ... M8: =M6*$C$8 -> 571249.68 | N8: =SUM(D8:M8) -> 4744047.8
B9: Trail/Pathway | C9: 0.11 | D9: =D6*$C$9 -> 110000 | E9: =E6*$C$9 -> 117425 | F9: =F6*$C$9 -> 125184.12 | G9: =G6*$C$9 -> 133292.41 | H9: =H6*$C$9 -> 138941.18 | I9: =I6*$C$9 -> 144759.42 | J9: =J6*$C$9 -> 150752.2 | K9: =K6*$C$9 -> 156924.77 | ... M9: =M6*$C$9 -> 169830.99 | N9: =SUM(D9:M9) -> 1410392.6
B10: Total | C10: =SUM(C7:C9) -> 1 | D10: =SUM(D7:D9) -> 1000000 | E10: =SUM(E7:E9) -> 1067500 | F10: =SUM(F7:F9) -> 1138037.5 | G10: =SUM(G7:G9) -> 1211749.2 | H10: =SUM(H7:H9) -> 1263101.7 | I10: =SUM(I7:I9) -> 1315994.7 | J10: =SUM(J7:J9) -> 1370474.6 | ... M10: =SUM(M7:M9) -> 1543918 | N10: =SUM(D10:M10) -> 12821751
B12: Sidewalk Projects
C13: Inflation | D13: 0.05 | E13: 0.05 | F13: 0.03 | G13: 0.03 | H13: 0.03 | I13: 0.03 | J13: 0.03 | K13: 0.03 | L13: 0.03 | M13: 0.03
C14: Year | D14: 1 | E14: 2 | F14: 3 | G14: 4 | H14: 5 | I14: 6 | J14: 7 | K14: 8 | L14: 9 | M14: 10
D15: =D3 -> 2023 | E15: =E3 -> 2024 | F15: =F3 -> 2025 | G15: =G3 -> 2026 | H15: =H3 -> 2027 | I15: =I3 -> 2028 | J15: =J3 -> 2029 | K15: =K3 -> 2030 | ... M15: =M3 -> 2032
C16: Sidewalk Fund | D16: 200000 | E16: 200000 | F16: 200000 | G16: 200000 | H16: 200000 | I16: 200000 | J16: 200000 | K16: 200000 | L16: 200000 | M16: 200000
C17: TBD Contribution | D17: =D7 -> 520000 | E17: =E7 -> 555100 | F17: =F7 -> 591779.5 | G17: =G7 -> 630109.58 | H17: =H7 -> 656812.86 | I17: =I7 -> 684317.25 | J17: =J7 -> 712646.77 | K17: =K7 -> 741826.17 | ... M17: =M7 -> 802837.39
C18: Beginning Fund Balance | D18: =SUM(D16:D17) -> 720000 | E18: =SUM(E16:E17)+D42 -> 1032840 | F18: =SUM(F16:F17)+E42 -> 1490270.9 | G18: =SUM(G16:G17)+F42 -> 2320380.5 | H18: =SUM(H16:H17)+G42 -> 1848233.1 | I18: =SUM(I16:I17)+H42 -> 2380984.3 | J18: =SUM(J16:J17)+I42 -> 3293631 | K18: =SUM(K16:K17)+J42 -> 2108109.9 | L18: =SUM(L16:L17)+K42 -> -1073525.3 | M18: =SUM(M16:M17)+L42 -> -3096989.2
C20: Project | D20: 2023 | E20: 2024 | F20: 2025 | G20: 2026 | H20: 2027 | I20: 2028 | J20: 2029 | K20: 2030 | L20: 2031 | M20: 2032
C21: 91st Ave SE (4th to Market) | D21: ='Sidewalk Projects - All'!W6*1.05^D14 -> 442260
C22: 91st Ave SE (8th to 4th St SE) | E22: ='Sidewalk Projects - All'!W7*1.05^E14 -> 334348.56
C23: 117th Ave NE (20th to 26th St NE) | G23: ='Sidewalk Projects - All'!W8*1.03^G14 -> 431398.52
C24: North Lakeshore Dr. (Main Street to 123rd Ave NE) | G24: ='Sidewalk Projects - All'!W10*1.03^G14 -> 897561.76
C25: Soper Hill (Lake Drive to SR9) | H25: ='Sidewalk Projects - All'!W9*1.03^H14 -> 351566.09
C26: 91st Ave SE (20th to 12th St. SE) | J26: ='Sidewalk Projects - All'!W12*1.03^J14 -> 2127347.3
C27: Hartford Drive (20th to 21st St. NE) | K27: ='Sidewalk Projects - All'!W16*1.03^K14 -> 334366.5
C28: Grade Road (Hartford to Library) | K28: ='Sidewalk Projects - All'!W15*1.03^K14 -> 1741808.9
C29: 113th Ave NE (32nd to 36th NE) | K29: ='Sidewalk Projects - All'!W13*1.03^K14 -> 995985.31
C30: 20th St NE (Main Street to 131st Ave SE | K30: ='Sidewalk Projects - All'!W14*1.03^K14 -> 1081355.5
C31: 123rd Ave NE(22nd to N. Lakeshore) | L31: ='Sidewalk Projects - All'!W18*1.03^L14 -> 131896.91
C32: 99th Ave NE (1st to Chapel Hill) | L32: ='Sidewalk Projects - All'!W20*1.03^L14 -> 1875867.2
C33: 83rd Ave NE (20th to 17th St. SE) | L33: ='Sidewalk Projects - All'!W19*1.03^L14 -> 1018537.3
C34: 103rd Ave SE (32nd to S. Lake Stevens) | M34: ='Sidewalk Projects - All'!W17*1.03^M14 -> 430203.76
C35: North Lakeshore Drive (123rd to Swim Beach) | M35: ='Sidewalk Projects - All'!W21*1.03^M14 -> 354729.42
C36: 99th Ave NE (Sunnycrest Elem to 30th St. NE) | M36: ='Sidewalk Projects - All'!W20*1.03^M14 -> 1932143.2 | N36: Unfunded
C37: 99th Ave SE (20th to 8th St. SE) | N37: ='Sidewalk Projects - All'!W23 -> 741312
C38: 4th St. NE (97th to 98th Drive NE) | N38: ='Sidewalk Projects - All'!W26 -> 1151280
C39: 20th St. SE (S.Lake Stevens Road to 113th Drive SE) | N39: ='Sidewalk Projects - All'!W25 -> 359424
C40: Project Cost Total | D40: =SUM(D21:D39) -> 442260 | E40: =SUM(E21:E39) -> 334348.56 | F40: =SUM(F21:F39) -> 0 | G40: =SUM(G21:G39) -> 1328960.3 | H40: =SUM(H21:H39) -> 351566.09 | I40: =SUM(I21:I39) -> 0 | J40: =SUM(J21:J39) -> 2127347.3 | K40: =SUM(K21:K39) -> 4153516.1 | ... M40: =SUM(M21:M39) -> 2717076.4
C42: Ending Fund Balance | D42: =D18-D40 -> 277740 | E42: =E18-E40 -> 698491.44 | F42: =F18-F40 -> 1490270.9 | G42: =G18-G40 -> 991420.23 | H42: =H18-H40 -> 1496667 | I42: =I18-I40 -> 2380984.3 | J42: =J18-J40 -> 1166283.8 | K42: =K18-K40 -> -2045406.2 | ... M42: =M18-M40 -> -5814065.6
B45: Roadway Projects
C46: Inflation | D46: 0.05 | E46: 0.05 | F46: 0.03 | G46: 0.03 | H46: 0.03 | I46: 0.03 | J46: 0.03 | K46: 0.03 | L46: 0.03 | M46: 0.03
C47: Year | D47: 1 | E47: 2 | F47: 3 | G47: 4 | H47: 5 | I47: 6 | J47: 7 | K47: 8 | L47: 9 | M47: 10
D48: 2023 | E48: 2024 | F48: 2025 | G48: 2026 | H48: 2027 | I48: 2028 | J48: 2029 | K48: 2030 | L48: 2031 | M48: 2032
C49: Overlay Budget | D49: 400000 | E49: 400000 | F49: 400000 | G49: 400000 | H49: 400000 | I49: 400000 | J49: 400000 | K49: 400000 | L49: 400000 | M49: 400000
C50: TBD Contribution | D50: =D8 -> 370000 | E50: =E8 -> 394975 | F50: =F8 -> 421073.88 | G50: =G8 -> 448347.2 | H50: =H8 -> 467347.62 | I50: =I8 -> 486918.04 | J50: =J8 -> 507075.59 | K50: =K8 -> 527837.85 | ... M50: =M8 -> 571249.68
C51: Beginning Fund Balance | D51: =SUM(D49:D50) -> 770000 | E51: =SUM(E49:E50)+D78 -> 914975 | F51: =SUM(F49:F50)+E78 -> 1086048.9 | G51: =SUM(G49:G50)+F78 -> 1284396.1 | H51: =SUM(H49:H50)+G78 -> 727223.11 | I51: =SUM(I49:I50)+H78 -> 964141.15 | J51: =SUM(J49:J50)+I78 -> 1221216.7 | K51: =SUM(K49:K50)+J78 -> 1499054.6 | L51: =SUM(L49:L50)+K78 -> 1798277.6 | M51: =SUM(M49:M50)+L78 -> 2119527.3
C53: Project | D53: 2023 | E53: 2024 | F53: 2025 | G53: 2026 | H53: 2027 | I53: 2028 | J53: 2029 | K53: 2030 | L53: 2031 | M53: 2032
C54: Current Annual Overlay | D54: 400000 | E54: 400000 | F54: 400000 | G54: 400000 | H54: 400000 | I54: 400000 | J54: 400000 | K54: 400000 | L54: 400000 | M54: 400000
C55: Annual Overlay Additional | D55: 250000 | E55: 250000 | F55: 250000 | G55: 250000 | H55: 250000 | I55: 250000 | J55: 250000 | K55: 250000 | L55: 250000 | M55: 250000
C56: Main Street (16th St NE to 20th St. NE) - 20% Match | G56: =('Roadway Projects - All'!R13*0.2)*1.05^G47 -> 774520.58
C57: 79th Ave SE Access Road (20th St. SE to 83rd Ave SE) | M57: ='Roadway Projects - All'!R13*1.03^M47 -> 4281717.6
C58: 91st Ave NE (Market Place to SR 204)
C78: Ending Fund Balance | D78: =D51-SUM(D54:D76) -> 120000 | E78: =E51-SUM(E54:E76) -> 264975 | F78: =F51-SUM(F54:F76) -> 436048.88 | G78: =G51-SUM(G54:G76) -> -140124.51 | H78: =H51-SUM(H54:H76) -> 77223.107 | I78: =I51-SUM(I54:I76) -> 314141.15 | J78: =J51-SUM(J54:J76) -> 571216.74 | K78: =K51-SUM(K54:K76) -> 849054.59 | ... M78: =M51-SUM(M54:M76) -> -2812190.3
B82: Trail Projects
C83: Inflation | D83: 0.05 | E83: 0.05 | F83: 0.03 | G83: 0.03 | H83: 0.03 | I83: 0.03 | J83: 0.03 | K83: 0.03 | L83: 0.03 | M83: 0.03
C84: Year | D84: 1 | E84: 2 | F84: 3 | G84: 4 | H84: 5 | I84: 6 | J84: 7 | K84: 8 | L84: 9 | M84: 10
D85: 2023 | E85: 2024 | F85: 2024 | G85: 2026 | H85: 2027 | I85: 2028 | J85: 2029 | K85: 2030 | L85: 2031 | M85: 2032
C86: Beginning Fund Balance | D86: =D9 -> 110000 | E86: =D116+E9 -> 227425 | F86: =E116+F9 -> 55903.225 | G86: =F116+G9 -> 189195.64 | H86: =G116+H9 -> 328136.82 | I86: =H116+I9 -> 472896.24 | J86: =I116+J9 -> 623648.44 | K86: =J116+K9 -> -129533.46 | L86: =K116+L9 -> -48851.955 | M86: =L116+M9 -> 120979.03 | N86: Comprehensive Plan Estimate - 2022
C88: Project
B89: 2022 Budget ($475K) | C89: Powerline Trail Phase I (20th St. SE to 8th St. SE) | E89: =(N89*1.05^2)-475000 -> 296705.9 | N89: 699960
C90: Powerline Trail Phase II (8th St. SE to Market Place) | J90: =740000*1.03^J84 -> 910106.66 | N90: =3700*200 -> 740000
C91: Hartford Road Walking Path | K91: =N91*1.03^K84 -> 63338.504 | N91: 50000
C92: Catherine Creek and Centennial Woods Trail | K92: =N92*1.03^K84 -> 19262.506 | N92: 15206
C116: Ending Fund Balance | D116: =D86-SUM(D91:D114) -> 110000 | E116: =E86-SUM(E89:E114) -> -69280.9 | F116: =F86-SUM(F89:F114) -> 55903.225 | G116: =G86-SUM(G89:G114) -> 189195.64 | H116: =H86-SUM(H89:H114) -> 328136.82 | I116: =I86-SUM(I89:I114) -> 472896.24 | J116: =J86-SUM(J89:J114) -> -286458.22 | K116: =K86-SUM(K89:K114) -> -212134.47 | L116: =L86-SUM(L89:L114) -> -48851.955 | M116: =M86-SUM(M89:M114) -> 120979.03
